Workbook

Sheet Eagle View
B82: Total Net Worth
A165: INVESTING
A250: Money Flow Repartition

Sheet Headquarters
B3: Recurring Expenses | M3: Expenses Per Month
C4: Amount | D4: Frequency | E4: Next Due Date | F4: Type | G4: Where ? | H4: Split | I4: Pay Cycle (Tuesday) | J4: Weeks Left | K4: Current Statut | M4: Student Loan | N4: Optus | O4: iCloud | P4: Youtube Premium | Q4: Microsoft Office | R4: ChatGPT | S4: Claude AI | T4: Total
B5: Optus | C5: 55 | D5: Monthly | E5: 46148 | F5: Bill | G5: Westpac Choice | H5: Solo to Bill | I5: 46175 | J5: =MAX(0, ROUNDUP(($I5-TODAY())/7, 0)) -> 3 | K5: Not Funded | M5: 110 | N5: 55 | O5: 14.99 | P5: 23 | Q5: 16 | R5: 29.99 | S5: 34 | T5: =SUM(N5:S5) -> 172.98
B6: ChatGPT | C6: 29.99 | D6: Monthly | E6: 46179 | F6: Subscription | G6: Westpac Choice | H6: Solo to Bill | I6: 46175 | J6: =MAX(0, ROUNDUP(($I6-TODAY())/7, 0)) -> 3 | K6: Not Funded
B7: Microsoft Office | C7: 16 | D7: Monthly | E7: 46148 | F7: Subscription | G7: Westpac Choice | H7: Solo to Bill | I7: 46175 | J7: =MAX(0, ROUNDUP(($I7-TODAY())/7, 0)) -> 3 | K7: Not Funded | M7: Expenses Per Week
B8: Youtube Premium | C8: 22.99 | D8: Monthly | E8: 46152 | F8: Subscription | G8: Westpac Choice | H8: Solo to Bill | I8: 46147 | J8: =MAX(0, ROUNDUP(($I8-TODAY())/7, 0)) -> 0 | K8: Not Funded | M8: Real Expenses | N8: Household Expenses | O8: Total
B9: Google One | C9: 3.5 | D9: Monthly | E9: 46162 | F9: Subscription | G9: Compte Courant | H9: Solo to French Acc | I9: 46189 | J9: =MAX(0, ROUNDUP(($I9-TODAY())/7, 0)) -> 5 | K9: Funded until June 20 | M9: ='Money Flow'!D577 -> 331.53688 | N9: ='Money Flow'!G577 -> 258.29625 | O9: =SUM(M9:N9) -> 589.83313
B10: Student Loan | C10: 113 | D10: Monthly | E10: 46193 | F10: Reimbursement | G10: Compte Courant | H10: Solo to French Acc | I10: 46189 | J10: =MAX(0, ROUNDUP(($I10-TODAY())/7, 0)) -> 5 | K10: Funded until June 20
B11: Claude AI | C11: 34 | D11: Monthly | E11: 46168 | F11: Subscription | G11: Westpac Choice | H11: Solo to Bill | I11: 46163 | J11: =MAX(0, ROUNDUP(($I11-TODAY())/7, 0)) -> 1 | K11: Not Funded
B12: Icloud | C12: 14.99 | D12: Monthly | E12: 46170 | F12: Subscription | G12: Westpac Choice | H12: Solo to Bill | I12: 46163 | J12: =MAX(0, ROUNDUP(($I12-TODAY())/7, 0)) -> 1 | K12: Not Funded
B13: Rent | C13: 150 | D13: Weekly | E13: 46161 | F13: Rent | G13: Westpac Choice | H13: Solo to Lily | I13: 46161 | J13: =MAX(0, ROUNDUP(($I13-TODAY())/7, 0)) -> 1 | K13: Not Funded
B14: Groceries (Joint Account) | C14: 200 | D14: Weekly | E14: 46161 | F14: Groce./Activ. | G14: Joint Acc | H14: Solo to Joint | I14: 46161 | J14: =MAX(0, ROUNDUP(($I14-TODAY())/7, 0)) -> 1 | K14: Not Funded
J17: Next Pay Day | K17: 46161
B20: Goal And Timelines
B21: Goal | C21: Type | D21: Current Amount | E21: Targeted Amount | F21: Remaining Amount | G21: Weekly Save Needed | H21: Targeted Date | I21: Weeks Left | J21: Progress (%) | K21: Priority
B22: Money To Move in Sydney | C22: Short Term | D22: 4015 | E22: 8000 | F22: =IF(E22="","", E22-D22) -> 3985 | G22: =IF($I22<=0, $F22, ROUND($F22/$I22,0)) -> 797 | H22: 46189 | I22: =MAX(0, ROUNDUP(($H22-TODAY())/7, 0)) -> 5 | J22: =IF($E22=0, 0, $D22/$E22) -> 0.501875 | K22: High
B23: Student Loan | C23: Medium Term | D23: =H44 -> 2445.5847 | E23: =J33 -> 8126 | F23: =IF(E23="","", E23-D23) -> 5680.4153 | G23: =IF($I23<=0, $F23, ROUND($F23/$I23,0)) -> 80 | H23: 46650 | I23: =MAX(0, ROUNDUP(($H23-TODAY())/7, 0)) -> 71 | J23: =IF($E23=0, 0, $D23/$E23) -> 0.300958 | K23: Medium
B24: Phiphi Reimbursement | C24: Medium Term | D24: 0 | E24: =D44 -> 1706.46 | F24: =IF(E24="","", E24-D24) -> 1706.46 | G24: =IF($I24<=0, $F24, ROUND($F24/$I24,0)) -> 24 | H24: 46650 | I24: =MAX(0, ROUNDUP(($H24-TODAY())/7, 0)) -> 71 | J24: =IF($E24=0, 0, $D24/$E24) -> 0 | K24: Medium
B25: Cash Buffer (Stage 2) | C25: Medium Term | D25: =C83 -> 1500 | E25: 10000 | F25: =IF(E25="","", E25-D25) -> 8500 | G25: =IF($I25<=0, $F25, ROUND($F25/$I25,0)) -> 258 | H25: 46386 | I25: =MAX(0, ROUNDUP(($H25-TODAY())/7, 0)) -> 33 | J25: =IF($E25=0, 0, $D25/$E25) -> 0.15 | K25: High
B26: House | C26: Long Term | D26: 0 | E26: 100000 | F26: =IF(E26="","", E26-D26) -> 100000 | G26: =IF($I26<=0, $F26, ROUND($F26/$I26,0)) -> 2174 | H26: 46478 | I26: =MAX(0, ROUNDUP(($H26-TODAY())/7, 0)) -> 46 | J26: =IF($E26=0, 0, $D26/$E26) -> 0 | K26: Low
B27: Investment | C27: Long Term | D27: =C86 -> 872.22531 | E27: 1000000 | F27: =IF(E27="","", E27-D27) -> 999127.77 | G27: =IF($I27<=0, $F27, ROUND($F27/$I27,0)) -> 1151 | H27: 52230 | I27: =MAX(0, ROUNDUP(($H27-TODAY())/7, 0)) -> 868 | J27: =IF($E27=0, 0, $D27/$E27) -> 0.00087222531 | K27: Low
B30: Student Loan
B31: Date | C31: Phiphi's Contribution | E31: My contribution | G31: Prélévement | I31: Loan Total Value / Remaining
C32: Eur | D32: Aud | E32: Eur | F32: Aud | G32: Eur | H32: Aud | I32: Eur | J32: Aud
B33: Rule | C33: 150 | D33: =C33*K78 -> 243.78 | E33: =G33-C33 -> 64.97 | F33: =E33*K78 -> 105.58924 | G33: 214.97 | H33: =G33*K78 -> 349.36924 | I33: 5000 | J33: =I33*K78 -> 8126
B34: 45950 | C34: 150 | D34: =C34*K78 -> 243.78 | E34: =G34-C34 -> 64.97 | F34: =E34*K78 -> 105.58924 | G34: 214.97 | H34: =G34*K78 -> 349.36924 | I34: =I33-G34 -> 4785.03 | J34: =J33-H34 -> 7776.6308
B35: 45981 | C35: 150 | D35: =C35*K78 -> 243.78 | E35: =G35-C35 -> 64.97 | F35: =E35*K78 -> 105.58924 | G35: 214.97 | H35: =G35*K78 -> 349.36924 | I35: =I34-G35 -> 4570.06 | J35: =J34-H35 -> 7427.2615
B36: 46011 | C36: 150 | D36: =C36*K78 -> 243.78 | E36: =G36-C36 -> 64.97 | F36: =E36*K78 -> 105.58924 | G36: 214.97 | H36: =G36*K78 -> 349.36924 | I36: =I35-G36 -> 4355.09 | J36: =J35-H36 -> 7077.8923
B37: 46042 | C37: 150 | D37: =C37*K78 -> 243.78 | E37: =G37-C37 -> 64.97 | F37: =E37*K78 -> 105.58924 | G37: 214.97 | H37: =G37*K78 -> 349.36924 | I37: =I36-G37 -> 4140.12 | J37: =J36-H37 -> 6728.523
B38: 46073 | C38: 150 | D38: =C38*K78 -> 243.78 | E38: =G38-C38 -> 64.97 | F38: =E38*K78 -> 105.58924 | G38: 214.97 | H38: =G38*K78 -> 349.36924 | I38: =I37-G38 -> 3925.15 | J38: =J37-H38 -> 6379.1538
B39: 46101 | C39: 150 | D39: =C39*K78 -> 243.78 | E39: =G39-C39 -> 64.97 | F39: =E39*K78 -> 105.58924 | G39: 214.97 | H39: =G39*K78 -> 349.36924 | I39: 3769.85 | J39: =J38-H39 -> 6029.7845
B40: 46132 | C40: 150 | D40: =C40*K78 -> 243.78 | E40: =G40-C40 -> 64.97 | F40: =E40*K78 -> 105.58924 | G40: 214.97 | H40: =G40*K78 -> 349.36924 | I40: =I39-G40 -> 3554.88 | J40: =J39-H40 -> 5680.4153
B41: 46162
B42: 46193
B43: 46223
B44: Total / Remaining | C44: =SUM(C34:C43) -> 1050 | D44: =SUM(D34:D43) -> 1706.46 | E44: =SUM(E34:E43) -> 454.79 | F44: =SUM(F34:F43) -> 739.12471 | G44: =SUM(G34:G43) -> 1504.79 | H44: =SUM(H34:H43) -> 2445.5847 | I44: =I40 -> 3554.88 | J44: =J40 -> 5680.4153
B47: Bank Statut (including Joint Acc)
C48: WestPac | E48: Commonwealth Bank | J48: LaBanque Postale
C49: Choice | D49: eSaver | E49: Daily Spending Acc | F49: Joint Expenses Acc | G49: Planned Expenses Acc | H49: Investing Cash Acc | I49: Emergency Fund Acc | J49: Compte Courant | K49: Livret Jeune | L49: Net Worth
B50: 24/1/2026 - 3pm | C50: 117.49 | D50: 15.03 | E50: 0 | F50: 202.62 | G50: 50.01 | H50: 0 | I50: 50.01 | J50: =7*K78 -> 11.3764 | K50: =12*K78 -> 19.5024 | L50: =SUM(C50:K50) -> 466.0388 | M50: 24/1/2026 - 3pm
B51: 25/1/2026 - 5pm | C51: 67.49 | D51: 15.03 | E51: 0 | F51: 120.79 | G51: 50.01 | H51: 0 | I51: 50.01 | J51: =7*K78 -> 11.3764 | K51: =12*K78 -> 19.5024 | L51: =SUM(C51:K51) -> 334.2088 | M51: 25/1/2026 - 5pm
B52: 1/2/2026 - 3pm | C52: 31 | D52: 205.01 | E52: 0 | F52: 162 | G52: 75 | H52: 0 | I52: 200 | J52: =4*K78 -> 6.5008 | K52: =12*K78 -> 19.5024 | L52: =SUM(C52:K52) -> 699.0132 | M52: 1/2/2026 - 3pm
B53: 5/2/2026 - 7am | C53: 152 | D53: 105 | E53: 0 | F53: 325.66 | G53: 75 | H53: 0 | I53: 330 | J53: =4*K78 -> 6.5008 | K53: =12*K78 -> 19.5024 | L53: =SUM(C53:K53) -> 1013.6632 | M53: 5/2/2026 - 7am
B54: 19/2/2026 - 12pm | C54: 49.59 | D54: 755 | E54: 0 | F54: 385.3 | G54: 75 | H54: 0 | I54: 330 | J54: =4*K78 -> 6.5008 | K54: =12*K78 -> 19.5024 | L54: =SUM(C54:K54) -> 1620.8932 | M54: 19/2/2026 - 12pm
B55: 23/2/2026 - 6pm | C55: 45.09 | D55: 755 | E55: 0 | F55: 261.36 | G55: 75 | H55: 0 | I55: 330 | J55: =18*K78 -> 29.2536 | K55: =12*K78 -> 19.5024 | L55: =SUM(C55:K55) -> 1515.206 | M55: 23/2/2026 - 6pm
B56: 12/3/2026 - 6pm | C56: 330 | D56: 10 | E56: 0 | F56: 244 | G56: 0 | H56: 0 | I56: 660 | J56: =365*K78 -> 593.198 | K56: =12*K78 -> 19.5024 | L56: =SUM(C56:K56) -> 1856.7004 | M56: 12/3/2026 - 6pm
B57: 21/3/2026 - 4pm | C57: 390 | D57: 10 | E57: 0 | F57: 200 | G57: 300 | H57: 0 | I57: 1575 | J57: =150*K78 -> 243.78 | K57: =12*K78 -> 19.5024 | L57: =SUM(C57:I57) -> 2475 | M57: 21/3/2026 - 4pm
B58: 26/3/2026 - 6pm | C58: 260 | D58: 50 | E58: 4 | F58: 47 | G58: 300 | H58: 0 | I58: 1175 | J58: =150*K78 -> 243.78 | K58: =12*K78 -> 19.5024 | L58: =SUM(C58:K58) -> 2099.2824 | M58: 26/3/2026 - 6pm
B59: 28/3/2026 - 11am | C59: 80 | D59: 101 | E59: 4 | F59: 153 | G59: 300 | H59: 0 | I59: 1175 | J59: =150*K78 -> 243.78 | K59: =12*K78 -> 19.5024 | L59: =SUM(C59:K59) -> 2076.2824 | M59: 28/3/2026 - 11am
B60: 29/3/2026 - 2pm | C60: 250 | D60: 101 | E60: 4 | F60: 300 | G60: 400 | H60: 0 | I60: 1975 | J60: =150*K78 -> 243.78 | K60: =12*K78 -> 19.5024 | L60: =SUM(C60:K60) -> 3293.2824 | M60: 29/3/2026 - 2pm
B61: 6/4/2026 - 10am | C61: 93 | D61: 21 | E61: 4 | F61: 30 | G61: 478 | H61: 400 | I61: 1500 | J61: =150*K78 -> 243.78 | K61: =12*K78 -> 19.5024 | L61: =SUM(C61:K61) -> 2789.2824 | M61: 6/4/2026 - 10am
B62: 8/4/2026 - 6pm | C62: 267 | D62: 20 | E62: 4 | F62: 66 | G62: 978 | H62: 500 | I62: 1500 | J62: =150*K78 -> 243.78 | K62: =12*K78 -> 19.5024 | L62: =SUM(C62:K62) -> 3598.2824 | M62: 8/4/2026 - 6pm
B63: 16/4/2026 - 7pm | C63: 80 | D63: 62 | E63: 4 | F63: 158 | G63: 1478 | H63: 300 | I63: 1500 | J63: =150*K78 -> 243.78 | K63: =12*K78 -> 19.5024 | L63: =+SUM(C63:K63) -> 3845.2824 | M63: 16/4/2026 - 7pm
B64: 22/4/2026 - 8pm | C64: 300 | D64: 2 | E64: 4 | F64: 215 | G64: 2078 | H64: 150 | I64: 1500 | J64: =75*K78 -> 121.89 | K64: =12*K78 -> 19.5024 | L64: =SUM(C64:K64) -> 4390.3924 | M64: 22/4/2026 - 8pm
B65: 26/4/2026 - 12pm | C65: 83 | D65: 6.5 | E65: 4.5 | F65: 112.5 | G65: 2078 | H65: 150 | I65: 1500 | J65: =71.5*K78 -> 116.2018 | K65: =12*K78 -> 19.5024 | L65: =SUM(C65:K65) -> 4070.2042 | M65: =B65 -> 26/4/2026 - 12pm
B66: 28/4/2026 - 9pm | C66: 294.5 | D66: 62 | E66: 4.5 | F66: 83 | G66: 2850 | H66: 100 | I66: 1500 | J66: =71.5*K78 -> 116.2018 | K66: =12*K78 -> 19.5024 | L66: =SUM(C66:K66) -> 5029.7042 | M66: =B66 -> 28/4/2026 - 9pm
B67: 4/5/2026 - 7am | C67: 0.25 | D67: 12.03 | E67: 4.5 | F67: 104.5 | G67: 2855 | H67: 101.93 | I67: 1500 | J67: =71.5*K78 -> 116.2018 | K67: =12*K78 -> 19.5024 | L67: =SUM(C67:K67) -> 4713.9142 | M67: =B67 -> 4/5/2026 - 7am
B68: 6/5/2026 - 7pm | C68: 68.27 | D68: 100 | E68: 1 | F68: 55 | G68: 3615 | H68: 52 | I68: 1500 | J68: =71.5*K78 -> 116.2018 | K68: =12*K78 -> 19.5024 | L68: =SUM(C68:K68) -> 5526.9742 | M68: =B68 -> 6/5/2026 - 7pm
B69: 13/5/2026 - 8pm | C69: 122 | D69: 50 | E69: 1 | F69: 151 | G69: 4365 | H69: 0 | I69: 1500 | J69: =71.5*K78 -> 116.2018 | K69: =12*K78 -> 19.5024 | L69: =SUM(C69:K69) -> 6324.7042 | M69: =B69 -> 13/5/2026 - 8pm
B70: 17/5/2026 - 7pm | C70: 17 | D70: 0 | E70: 0 | F70: 289 | G70: 4015 | H70: 2 | I70: 1500 | J70: =71.5*K78 -> 116.2018 | K70: =12*K78 -> 19.5024 | L70: =SUM(C70:K70) -> 5958.7042 | M70: =B70 -> 17/5/2026 - 7pm
L71: =SUM(C71:K71) -> 0 | M71: =B71 -> 0
L72: =SUM(C72:K72) -> 0 | M72: =B72 -> 0
L73: =SUM(C73:K73) -> 0 | M73: =B73 -> 0
B74: ACTUAL BALANCE= | C74: =C70 -> 17 | D74: =D70 -> 0 | E74: =E70 -> 0 | F74: =F70 -> 289 | G74: =G70 -> 4015 | H74: =H70 -> 2 | I74: =I70 -> 1500 | J74: =J70 -> 116.2018 | K74: =K70 -> 19.5024 | L74: =SUM(C74:K74) -> 5958.7042
B76: Bank Statut (Excluding Joint) | I76: EUR To AUD
B77: Bank | C77: =SUM(C78:C85) -> 5669.7042 | I77: #VALUE! | J77: EUR | K77: AUD
B78: =C49 -> Choice | C78: =C74 -> 17 | J78: 1 | K78: {=_xlfn.FIELDVALUE(I77,"Price")} -> 1.6252
B79: =D49 -> eSaver | C79: =D74 -> 0
B80: =E49 -> Daily Spending Acc | C80: =E74 -> 0
B81: =G49 -> Planned Expenses Acc | C81: =G74 -> 4015
B82: =H49 -> Investing Cash Acc | C82: =H74 -> 2
B83: =I49 -> Emergency Fund Acc | C83: =I74 -> 1500
B84: LaBanquePoste CC | C84: =J74 -> 116.2018
B85: Livret Jeune | C85: =K74 -> 19.5024
B86: Investment | C86: =SUM(C87:C90) -> 872.22531
B87: Bitcoin | C87: =Investing!C31 -> 330.21314
B88: ETF Betashares | C88: =SUM(Investing!I17,Investing!O17) -> 420.07129
B89: CSL | C89: 28
B90: ETF Stake | C90: =Investing!AA11 -> 93.940869
B91: Superannuation | C91: =SUM(C92:C92) -> 7362.52
B92: UniSuper | C92: 7362.52
B93: Liquid Net Worth | C93: =SUM(C77,C86) -> 6541.9295
B94: Total Net Worth | C94: =SUM(C91,C93) -> 13904.45
B97: Wealth Repartition
B98: Operational Cash Flow | C98: =SUM(C78,C84,C80) -> 133.2018 | D98: =(C98/C103) -> 0.0095811749
B99: Future Spending | C99: =SUM(C81) -> 4015 | D99: =(C99/C103) -> 0.28879803
B100: Savings | C100: =SUM(C79,C83,C85) -> 1519.5024 | D100: =(C100/C103) -> 0.10929746
B101: Investment | C101: =SUM(C87:C90) -> 872.22531 | D101: =(C101/C103) -> 0.062738966
B102: Superannuation | C102: =C92 -> 7362.52 | D102: =(C102/C103) -> 0.52958437
B103: Total | C103: =SUM(C98:C102) -> 13902.45 | D103: =SUM(D98:D102) -> 1

Sheet Money Flow
B2: FLOW OF THE WEEK
B3: Week | C3: Date | D3: Description | E3: Flow Type | F3: Source Account | G3: Destination Account | H3: Amount | I3: Category (Economic Role) | N3: Real Expense Amt | O3: Internal Transfer Amt | P3: Saving Allocation Amt | Q3: Investment Amt | R3: Debt Repayment Amt | S3: Joint Account Amt | T3: Income Amt
A4: 27/1/26 -> 2/2/26 | B4: 27/1/26 -> 2/2/26 | C4: 46049 | D4: Pay Sapien | E4: Income | F4: Sapien | G4: WestPac Everyday | H4: 1316.75 | I4: Salary | N4: =IF(OR(E4="Personal Expense",E4="Recurring Expense"),H4,0) -> 0 | O4: =IF(E4="Internal Transfer",H4,0) -> 0 | P4: =IF(E4="Saving Allocation",H4,0) -> 0 | Q4: =IF(E4="Investment",H4,0) -> 0 | R4: =IF(E4="Debt Repayment",H4,0) -> 0 | S4: =IF(E4="Joint Account",H4,0) -> 0 | T4: =IF(E4="Income",H4,0) -> 1316.75
A5: 27/1/26 -> 2/2/26 | C5: 46049 | D5: Bills Contribution | E5: Recurring Expense | F5: WestPac Everyday | G5: Lily | H5: 150 | I5: Rent | N5: =IF(OR(E5="Personal Expense",E5="Recurring Expense"),H5,0) -> 150 | O5: =IF(E5="Internal Transfer",H5,0) -> 0 | P5: =IF(E5="Saving Allocation",H5,0) -> 0 | Q5: =IF(E5="Investment",H5,0) -> 0 | R5: =IF(E5="Debt Repayment",H5,0) -> 0 | S5: =IF(E5="Joint Account",H5,0) -> 0 | T5: =IF(E5="Income",H5,0) -> 0
A6: 27/1/26 -> 2/2/26 | C6: 46049 | D6: Reimboursement Lily | E6: Debt Repayment | F6: WestPac Everyday | G6: Lily | H6: 375 | I6: Debt | N6: =IF(OR(E6="Personal Expense",E6="Recurring Expense"),H6,0) -> 0 | O6: =IF(E6="Internal Transfer",H6,0) -> 0 | P6: =IF(E6="Saving Allocation",H6,0) -> 0 | Q6: =IF(E6="Investment",H6,0) -> 0 | R6: =IF(E6="Debt Repayment",H6,0) -> 375 | S6: =IF(E6="Joint Account",H6,0) -> 0 | T6: =IF(E6="Income",H6,0) -> 0
A7: 27/1/26 -> 2/2/26 | C7: 46049 | D7: Transfer To Joint Account | E7: Joint Account | F7: WestPac Everyday | G7: Joint Account | H7: 200 | I7: Housing | N7: =IF(OR(E7="Personal Expense",E7="Recurring Expense"),H7,0) -> 0 | O7: =IF(E7="Internal Transfer",H7,0) -> 0 | P7: =IF(E7="Saving Allocation",H7,0) -> 0 | Q7: =IF(E7="Investment",H7,0) -> 0 | R7: =IF(E7="Debt Repayment",H7,0) -> 0 | S7: =IF(E7="Joint Account",H7,0) -> 200 | T7: =IF(E7="Income",H7,0) -> 0
A8: 27/1/26 -> 2/2/26 | C8: 46049 | D8: BTC Buy | E8: Investment | F8: WestPac Everyday | G8: OKX | H8: 15 | I8: Investment | N8: =IF(OR(E8="Personal Expense",E8="Recurring Expense"),H8,0) -> 0 | O8: =IF(E8="Internal Transfer",H8,0) -> 0 | P8: =IF(E8="Saving Allocation",H8,0) -> 0 | Q8: =IF(E8="Investment",H8,0) -> 15 | R8: =IF(E8="Debt Repayment",H8,0) -> 0 | S8: =IF(E8="Joint Account",H8,0) -> 0 | T8: =IF(E8="Income",H8,0) -> 0
A9: 27/1/26 -> 2/2/26 | C9: 46050 | D9: Flight Ticket Sydney | E9: Personal Expense | F9: WestPac Everyday | G9: External | H9: 56.4 | I9: Transport | N9: =IF(OR(E9="Personal Expense",E9="Recurring Expense"),H9,0) -> 56.4 | O9: =IF(E9="Internal Transfer",H9,0) -> 0 | P9: =IF(E9="Saving Allocation",H9,0) -> 0 | Q9: =IF(E9="Investment",H9,0) -> 0 | R9: =IF(E9="Debt Repayment",H9,0) -> 0 | S9: =IF(E9="Joint Account",H9,0) -> 0 | T9: =IF(E9="Income",H9,0) -> 0
A10: 27/1/26 -> 2/2/26 | C10: 46051 | D10: Food at Work | E10: Personal Expense | F10: WestPac Everyday | G10: External | H10: 8 | I10: Food/Drink | N10: =IF(OR(E10="Personal Expense",E10="Recurring Expense"),H10,0) -> 8 | O10: =IF(E10="Internal Transfer",H10,0) -> 0 | P10: =IF(E10="Saving Allocation",H10,0) -> 0 | Q10: =IF(E10="Investment",H10,0) -> 0 | R10: =IF(E10="Debt Repayment",H10,0) -> 0 | S10: =IF(E10="Joint Account",H10,0) -> 0 | T10: =IF(E10="Income",H10,0) -> 0
A11: 27/1/26 -> 2/2/26 | C11: 46051 | D11: Icloud | E11: Recurring Expense | F11: WestPac Everyday | G11: External | H11: 14.99 | I11: Subscription | N11: =IF(OR(E11="Personal Expense",E11="Recurring Expense"),H11,0) -> 14.99 | O11: =IF(E11="Internal Transfer",H11,0) -> 0 | P11: =IF(E11="Saving Allocation",H11,0) -> 0 | Q11: =IF(E11="Investment",H11,0) -> 0 | R11: =IF(E11="Debt Repayment",H11,0) -> 0 | S11: =IF(E11="Joint Account",H11,0) -> 0 | T11: =IF(E11="Income",H11,0) -> 0
A12: 27/1/26 -> 2/2/26 | C12: 46052 | D12: Food at Work | E12: Personal Expense | F12: WestPac Everyday | G12: External | H12: 8 | I12: Food/Drink | N12: =IF(OR(E12="Personal Expense",E12="Recurring Expense"),H12,0) -> 8 | O12: =IF(E12="Internal Transfer",H12,0) -> 0 | P12: =IF(E12="Saving Allocation",H12,0) -> 0 | Q12: =IF(E12="Investment",H12,0) -> 0 | R12: =IF(E12="Debt Repayment",H12,0) -> 0 | S12: =IF(E12="Joint Account",H12,0) -> 0 | T12: =IF(E12="Income",H12,0) -> 0
A13: 27/1/26 -> 2/2/26 | C13: 46053 | D13: Buffer for Upcoming Bills | E13: Internal Transfer | F13: WestPac Everyday | G13: WestPac Savings | H13: 105 | I13: Buffer (To spend) | N13: =IF(OR(E13="Personal Expense",E13="Recurring Expense"),H13,0) -> 0 | O13: =IF(E13="Internal Transfer",H13,0) -> 105 | P13: =IF(E13="Saving Allocation",H13,0) -> 0 | Q13: =IF(E13="Investment",H13,0) -> 0 | R13: =IF(E13="Debt Repayment",H13,0) -> 0 | S13: =IF(E13="Joint Account",H13,0) -> 0 | T13: =IF(E13="Income",H13,0) -> 0
A14: 27/1/26 -> 2/2/26 | C14: 46053 | D14: Buffer for Dentist | E14: Personal Expense | F14: WestPac Everyday | G14: LaBanquePostale | H14: 100 | I14: Buffer (To spend) | N14: =IF(OR(E14="Personal Expense",E14="Recurring Expense"),H14,0) -> 100 | O14: =IF(E14="Internal Transfer",H14,0) -> 0 | P14: =IF(E14="Saving Allocation",H14,0) -> 0 | Q14: =IF(E14="Investment",H14,0) -> 0 | R14: =IF(E14="Debt Repayment",H14,0) -> 0 | S14: =IF(E14="Joint Account",H14,0) -> 0 | T14: =IF(E14="Income",H14,0) -> 0
A15: 27/1/26 -> 2/2/26 | C15: 46053 | D15: Sandwich Mama | E15: Personal Expense | F15: WestPac Everyday | G15: External | H15: 11 | I15: Food/Drink | N15: =IF(OR(E15="Personal Expense",E15="Recurring Expense"),H15,0) -> 11 | O15: =IF(E15="Internal Transfer",H15,0) -> 0 | P15: =IF(E15="Saving Allocation",H15,0) -> 0 | Q15: =IF(E15="Investment",H15,0) -> 0 | R15: =IF(E15="Debt Repayment",H15,0) -> 0 | S15: =IF(E15="Joint Account",H15,0) -> 0 | T15: =IF(E15="Income",H15,0) -> 0
A16: 27/1/26 -> 2/2/26 | C16: 46054 | D16: Buffer for Emerg. Cash | E16: Saving Allocation | F16: WestPac Everyday | G16: Emergency Fund | H16: 200 | I16: Savings | N16: =IF(OR(E16="Personal Expense",E16="Recurring Expense"),H16,0) -> 0 | O16: =IF(E16="Internal Transfer",H16,0) -> 0 | P16: =IF(E16="Saving Allocation",H16,0) -> 200 | Q16: =IF(E16="Investment",H16,0) -> 0 | R16: =IF(E16="Debt Repayment",H16,0) -> 0 | S16: =IF(E16="Joint Account",H16,0) -> 0 | T16: =IF(E16="Income",H16,0) -> 0
A17: 27/1/26 -> 2/2/26 | C17: 46054 | D17: Fitness weights | E17: Personal Expense | F17: WestPac Everyday | G17: External | H17: 60 | I17: Leisure | N17: =IF(OR(E17="Personal Expense",E17="Recurring Expense"),H17,0) -> 60 | O17: =IF(E17="Internal Transfer",H17,0) -> 0 | P17: =IF(E17="Saving Allocation",H17,0) -> 0 | Q17: =IF(E17="Investment",H17,0) -> 0 | R17: =IF(E17="Debt Repayment",H17,0) -> 0 | S17: =IF(E17="Joint Account",H17,0) -> 0 | T17: =IF(E17="Income",H17,0) -> 0
A18: 27/1/26 -> 2/2/26 | N18: =IF(OR(E18="Personal Expense",E18="Recurring Expense"),H18,0) -> 0 | O18: =IF(E18="Internal Transfer",H18,0) -> 0 | P18: =IF(E18="Saving Allocation",H18,0) -> 0 | Q18: =IF(E18="Investment",H18,0) -> 0 | R18: =IF(E18="Debt Repayment",H18,0) -> 0 | S18: =IF(E18="Joint Account",H18,0) -> 0 | T18: =IF(E18="Income",H18,0) -> 0
A19: 27/1/26 -> 2/2/26 | N19: =IF(OR(E19="Personal Expense",E19="Recurring Expense"),H19,0) -> 0 | O19: =IF(E19="Internal Transfer",H19,0) -> 0 | P19: =IF(E19="Saving Allocation",H19,0) -> 0 | Q19: =IF(E19="Investment",H19,0) -> 0 | R19: =IF(E19="Debt Repayment",H19,0) -> 0 | S19: =IF(E19="Joint Account",H19,0) -> 0 | T19: =IF(E19="Income",H19,0) -> 0
A20: 27/1/26 -> 2/2/26 | B20: Pay | H20: =SUMIF(E4:E17,"Income",H4:H17) -> 1316.75 | N20: =IF(OR(E20="Personal Expense",E20="Recurring Expense"),H20,0) -> 0 | O20: =IF(E20="Internal Transfer",H20,0) -> 0 | P20: =IF(E20="Saving Allocation",H20,0) -> 0 | Q20: =IF(E20="Investment",H20,0) -> 0 | R20: =IF(E20="Debt Repayment",H20,0) -> 0 | S20: =IF(E20="Joint Account",H20,0) -> 0 | T20: =IF(E20="Income",H20,0) -> 0
A21: 27/1/26 -> 2/2/26 | F21: Total Household Expenses | H21: =SUMIF(E4:E17,"Joint Account",H4:H17) -> 200 | N21: =IF(OR(E21="Personal Expense",E21="Recurring Expense"),H21,0) -> 0 | O21: =IF(E21="Internal Transfer",H21,0) -> 0 | P21: =IF(E21="Saving Allocation",H21,0) -> 0 | Q21: =IF(E21="Investment",H21,0) -> 0 | R21: =IF(E21="Debt Repayment",H21,0) -> 0 | S21: =IF(E21="Joint Account",H21,0) -> 0 | T21: =IF(E21="Income",H21,0) -> 0
A22: 27/1/26 -> 2/2/26 | B22: Total Reccuring Expenses | H22: =SUMIF(E4:E17,"Recurring Expense",H4:H17) -> 164.99 | N22: =IF(OR(E22="Personal Expense",E22="Recurring Expense"),H22,0) -> 0 | O22: =IF(E22="Internal Transfer",H22,0) -> 0 | P22: =IF(E22="Saving Allocation",H22,0) -> 0 | Q22: =IF(E22="Investment",H22,0) -> 0 | R22: =IF(E22="Debt Repayment",H22,0) -> 0 | S22: =IF(E22="Joint Account",H22,0) -> 0 | T22: =IF(E22="Income",H22,0) -> 0
A23: 27/1/26 -> 2/2/26 | B23: Total Investing | H23: =SUMIF(E4:E17,"Investment",H4:H17) -> 15 | N23: =IF(OR(E23="Personal Expense",E23="Recurring Expense"),H23,0) -> 0 | O23: =IF(E23="Internal Transfer",H23,0) -> 0 | P23: =IF(E23="Saving Allocation",H23,0) -> 0 | Q23: =IF(E23="Investment",H23,0) -> 0 | R23: =IF(E23="Debt Repayment",H23,0) -> 0 | S23: =IF(E23="Joint Account",H23,0) -> 0 | T23: =IF(E23="Income",H23,0) -> 0
A24: 27/1/26 -> 2/2/26 | B24: Total Savings | H24: =SUMIF(E4:E17,"Saving Allocation",H4:H17) -> 200 | N24: =IF(OR(E24="Personal Expense",E24="Recurring Expense"),H24,0) -> 0 | O24: =IF(E24="Internal Transfer",H24,0) -> 0 | P24: =IF(E24="Saving Allocation",H24,0) -> 0 | Q24: =IF(E24="Investment",H24,0) -> 0 | R24: =IF(E24="Debt Repayment",H24,0) -> 0 | S24: =IF(E24="Joint Account",H24,0) -> 0 | T24: =IF(E24="Income",H24,0) -> 0
A25: 27/1/26 -> 2/2/26 | B25: Total Personnal Expenses | H25: =SUMIF(E4:E17,"Personal Expense",H4:H17) -> 243.4 | N25: =IF(OR(E25="Personal Expense",E25="Recurring Expense"),H25,0) -> 0 | O25: =IF(E25="Internal Transfer",H25,0) -> 0 | P25: =IF(E25="Saving Allocation",H25,0) -> 0 | Q25: =IF(E25="Investment",H25,0) -> 0 | R25: =IF(E25="Debt Repayment",H25,0) -> 0 | S25: =IF(E25="Joint Account",H25,0) -> 0 | T25: =IF(E25="Income",H25,0) -> 0
A26: 27/1/26 -> 2/2/26 | G26: Total Debt Repayments | H26: =SUMIF(E4:E17,"Debt Repayment",H4:H17) -> 375 | N26: =IF(OR(E26="Personal Expense",E26="Recurring Expense"),H26,0) -> 0 | O26: =IF(E26="Internal Transfer",H26,0) -> 0 | P26: =IF(E26="Saving Allocation",H26,0) -> 0 | Q26: =IF(E26="Investment",H26,0) -> 0 | R26: =IF(E26="Debt Repayment",H26,0) -> 0 | S26: =IF(E26="Joint Account",H26,0) -> 0 | T26: =IF(E26="Income",H26,0) -> 0
A27: 27/1/26 -> 2/2/26 | G27: TOTAL | H27: =H22+H25+H21+H23+H26+H24 -> 1198.39 | N27: =IF(OR(E27="Personal Expense",E27="Recurring Expense"),H27,0) -> 0 | O27: =IF(E27="Internal Transfer",H27,0) -> 0 | P27: =IF(E27="Saving Allocation",H27,0) -> 0 | Q27: =IF(E27="Investment",H27,0) -> 0 | R27: =IF(E27="Debt Repayment",H27,0) -> 0 | S27: =IF(E27="Joint Account",H27,0) -> 0 | T27: =IF(E27="Income",H27,0) -> 0
A28: 27/1/26 -> 2/2/26 | B28: TRUE WEEKLY SURPLUS | H28: =H20-(H22+H25)-H21-H23-H26-H24 -> 118.36 | N28: =IF(OR(E28="Personal Expense",E28="Recurring Expense"),H28,0) -> 0 | O28: =IF(E28="Internal Transfer",H28,0) -> 0 | P28: =IF(E28="Saving Allocation",H28,0) -> 0 | Q28: =IF(E28="Investment",H28,0) -> 0 | R28: =IF(E28="Debt Repayment",H28,0) -> 0 | S28: =IF(E28="Joint Account",H28,0) -> 0 | T28: =IF(E28="Income",H28,0) -> 0
B29: TRUE WEEKLY SURPLUS W/O SAVINGS | H29: =H28+SUMIFS($H:$H,$A:$A,A28,$E:$E,"Saving Allocation") -> 318.36
A30: 27/1/26 -> 2/2/26 | N30: =IF(OR(E30="Personal Expense",E30="Recurring Expense"),H30,0) -> 0 | O30: =IF(E30="Internal Transfer",H30,0) -> 0 | P30: =IF(E30="Saving Allocation",H30,0) -> 0 | Q30: =IF(E30="Investment",H30,0) -> 0 | R30: =IF(E30="Debt Repayment",H30,0) -> 0 | S30: =IF(E30="Joint Account",H30,0) -> 0 | T30: =IF(E30="Income",H30,0) -> 0
A31: 3/2/26 -> 9/2/26 | B31: 3/2/26 -> 9/2/26 | C31: 46056 | D31: Pay Sapien | E31: Income | F31: Sapien | G31: WestPac Everyday | H31: 1078.75 | I31: Salary | N31: =IF(OR(E31="Personal Expense",E31="Recurring Expense"),H31,0) -> 0 | O31: =IF(E31="Internal Transfer",H31,0) -> 0 | P31: =IF(E31="Saving Allocation",H31,0) -> 0 | Q31: =IF(E31="Investment",H31,0) -> 0 | R31: =IF(E31="Debt Repayment",H31,0) -> 0 | S31: =IF(E31="Joint Account",H31,0) -> 0 | T31: =IF(E31="Income",H31,0) -> 1078.75
A32: 3/2/26 -> 9/2/26 | C32: 46056 | D32: Bills Contribution | E32: Recurring Expense | F32: WestPac Everyday | G32: Lily | H32: 150 | I32: Rent | N32: =IF(OR(E32="Personal Expense",E32="Recurring Expense"),H32,0) -> 150 | O32: =IF(E32="Internal Transfer",H32,0) -> 0 | P32: =IF(E32="Saving Allocation",H32,0) -> 0 | Q32: =IF(E32="Investment",H32,0) -> 0 | R32: =IF(E32="Debt Repayment",H32,0) -> 0 | S32: =IF(E32="Joint Account",H32,0) -> 0 | T32: =IF(E32="Income",H32,0) -> 0
A33: 3/2/26 -> 9/2/26 | C33: 46056 | D33: Reimboursement Lily | E33: Debt Repayment | F33: WestPac Everyday | G33: Lily | H33: 375 | I33: Debt | N33: =IF(OR(E33="Personal Expense",E33="Recurring Expense"),H33,0) -> 0 | O33: =IF(E33="Internal Transfer",H33,0) -> 0 | P33: =IF(E33="Saving Allocation",H33,0) -> 0 | Q33: =IF(E33="Investment",H33,0) -> 0 | R33: =IF(E33="Debt Repayment",H33,0) -> 375 | S33: =IF(E33="Joint Account",H33,0) -> 0 | T33: =IF(E33="Income",H33,0) -> 0
A34: 3/2/26 -> 9/2/26 | C34: 46056 | D34: Transfer To Joint Account | E34: Joint Account | F34: WestPac Everyday | G34: Joint Account | H34: 200 | I34: Housing | N34: =IF(OR(E34="Personal Expense",E34="Recurring Expense"),H34,0) -> 0 | O34: =IF(E34="Internal Transfer",H34,0) -> 0 | P34: =IF(E34="Saving Allocation",H34,0) -> 0 | Q34: =IF(E34="Investment",H34,0) -> 0 | R34: =IF(E34="Debt Repayment",H34,0) -> 0 | S34: =IF(E34="Joint Account",H34,0) -> 200 | T34: =IF(E34="Income",H34,0) -> 0
A35: 3/2/26 -> 9/2/26 | C35: 46057 | D35: BTC Buy | E35: Investment | F35: WestPac Everyday | G35: OKX | H35: 15 | I35: Investment | N35: =IF(OR(E35="Personal Expense",E35="Recurring Expense"),H35,0) -> 0 | O35: =IF(E35="Internal Transfer",H35,0) -> 0 | P35: =IF(E35="Saving Allocation",H35,0) -> 0 | Q35: =IF(E35="Investment",H35,0) -> 15 | R35: =IF(E35="Debt Repayment",H35,0) -> 0 | S35: =IF(E35="Joint Account",H35,0) -> 0 | T35: =IF(E35="Income",H35,0) -> 0
A36: 3/2/26 -> 9/2/26 | C36: 46057 | D36: Dentist | E36: Personal Expense | F36: WestPac Everyday | G36: External | H36: 80 | I36: Repayment | N36: =IF(OR(E36="Personal Expense",E36="Recurring Expense"),H36,0) -> 80 | O36: =IF(E36="Internal Transfer",H36,0) -> 0 | P36: =IF(E36="Saving Allocation",H36,0) -> 0 | Q36: =IF(E36="Investment",H36,0) -> 0 | R36: =IF(E36="Debt Repayment",H36,0) -> 0 | S36: =IF(E36="Joint Account",H36,0) -> 0 | T36: =IF(E36="Income",H36,0) -> 0
A37: 3/2/26 -> 9/2/26 | C37: 46057 | D37: Buffer for Emerg. Cash | E37: Saving Allocation | F37: WestPac Everyday | G37: Emergency Fund | H37: 130 | I37: Savings | N37: =IF(OR(E37="Personal Expense",E37="Recurring Expense"),H37,0) -> 0 | O37: =IF(E37="Internal Transfer",H37,0) -> 0 | P37: =IF(E37="Saving Allocation",H37,0) -> 130 | Q37: =IF(E37="Investment",H37,0) -> 0 | R37: =IF(E37="Debt Repayment",H37,0) -> 0 | S37: =IF(E37="Joint Account",H37,0) -> 0 | T37: =IF(E37="Income",H37,0) -> 0
A38: 3/2/26 -> 9/2/26 | C38: 46061 | D38: Transfer To Joint Account | E38: Joint Account | F38: WestPac Everyday | G38: Joint Account | H38: 50 | I38: Housing | N38: =IF(OR(E38="Personal Expense",E38="Recurring Expense"),H38,0) -> 0 | O38: =IF(E38="Internal Transfer",H38,0) -> 0 | P38: =IF(E38="Saving Allocation",H38,0) -> 0 | Q38: =IF(E38="Investment",H38,0) -> 0 | R38: =IF(E38="Debt Repayment",H38,0) -> 0 | S38: =IF(E38="Joint Account",H38,0) -> 50 | T38: =IF(E38="Income",H38,0) -> 0
A39: 3/2/26 -> 9/2/26 | C39: 46062 | D39: Sandwich at Work | E39: Personal Expense | F39: WestPac Everyday | G39: External | H39: 7.63 | I39: Food/Drink | N39: =IF(OR(E39="Personal Expense",E39="Recurring Expense"),H39,0) -> 7.63 | O39: =IF(E39="Internal Transfer",H39,0) -> 0 | P39: =IF(E39="Saving Allocation",H39,0) -> 0 | Q39: =IF(E39="Investment",H39,0) -> 0 | R39: =IF(E39="Debt Repayment",H39,0) -> 0 | S39: =IF(E39="Joint Account",H39,0) -> 0 | T39: =IF(E39="Income",H39,0) -> 0
A40: 3/2/26 -> 9/2/26 | N40: =IF(OR(E40="Personal Expense",E40="Recurring Expense"),H40,0) -> 0 | O40: =IF(E40="Internal Transfer",H40,0) -> 0 | P40: =IF(E40="Saving Allocation",H40,0) -> 0 | Q40: =IF(E40="Investment",H40,0) -> 0 | R40: =IF(E40="Debt Repayment",H40,0) -> 0 | S40: =IF(E40="Joint Account",H40,0) -> 0 | T40: =IF(E40="Income",H40,0) -> 0
A41: 3/2/26 -> 9/2/26 | B41: Pay | H41: =SUMIF(E31:E39,"Income",H31:H39) -> 1078.75 | N41: =IF(OR(E41="Personal Expense",E41="Recurring Expense"),H41,0) -> 0 | O41: =IF(E41="Internal Transfer",H41,0) -> 0 | P41: =IF(E41="Saving Allocation",H41,0) -> 0 | Q41: =IF(E41="Investment",H41,0) -> 0 | R41: =IF(E41="Debt Repayment",H41,0) -> 0 | S41: =IF(E41="Joint Account",H41,0) -> 0 | T41: =IF(E41="Income",H41,0) -> 0
A42: 3/2/26 -> 9/2/26 | F42: Total Household Expenses | H42: =SUMIF(E31:E39,"Joint Account",H31:H39) -> 250 | N42: =IF(OR(E42="Personal Expense",E42="Recurring Expense"),H42,0) -> 0 | O42: =IF(E42="Internal Transfer",H42,0) -> 0 | P42: =IF(E42="Saving Allocation",H42,0) -> 0 | Q42: =IF(E42="Investment",H42,0) -> 0 | R42: =IF(E42="Debt Repayment",H42,0) -> 0 | S42: =IF(E42="Joint Account",H42,0) -> 0 | T42: =IF(E42="Income",H42,0) -> 0
A43: 3/2/26 -> 9/2/26 | B43: Total Reccuring Expenses | H43: =SUMIF(E31:E39,"Recurring Expense",H31:H39) -> 150 | N43: =IF(OR(E43="Personal Expense",E43="Recurring Expense"),H43,0) -> 0 | O43: =IF(E43="Internal Transfer",H43,0) -> 0 | P43: =IF(E43="Saving Allocation",H43,0) -> 0 | Q43: =IF(E43="Investment",H43,0) -> 0 | R43: =IF(E43="Debt Repayment",H43,0) -> 0 | S43: =IF(E43="Joint Account",H43,0) -> 0 | T43: =IF(E43="Income",H43,0) -> 0
A44: 3/2/26 -> 9/2/26 | B44: Total Investing | H44: =SUMIF(E31:E39,"Investment",H31:H39) -> 15 | N44: =IF(OR(E44="Personal Expense",E44="Recurring Expense"),H44,0) -> 0 | O44: =IF(E44="Internal Transfer",H44,0) -> 0 | P44: =IF(E44="Saving Allocation",H44,0) -> 0 | Q44: =IF(E44="Investment",H44,0) -> 0 | R44: =IF(E44="Debt Repayment",H44,0) -> 0 | S44: =IF(E44="Joint Account",H44,0) -> 0 | T44: =IF(E44="Income",H44,0) -> 0
A45: 3/2/26 -> 9/2/26 | B45: Total Savings | H45: =SUMIF(E31:E39,"Saving Allocation",H31:H39) -> 130 | N45: =IF(OR(E45="Personal Expense",E45="Recurring Expense"),H45,0) -> 0 | O45: =IF(E45="Internal Transfer",H45,0) -> 0 | P45: =IF(E45="Saving Allocation",H45,0) -> 0 | Q45: =IF(E45="Investment",H45,0) -> 0 | R45: =IF(E45="Debt Repayment",H45,0) -> 0 | S45: =IF(E45="Joint Account",H45,0) -> 0 | T45: =IF(E45="Income",H45,0) -> 0
A46: 3/2/26 -> 9/2/26 | B46: Total Personnal Expenses | H46: =SUMIF(E31:E39,"Personal Expense",H31:H39) -> 87.63 | N46: =IF(OR(E46="Personal Expense",E46="Recurring Expense"),H46,0) -> 0 | O46: =IF(E46="Internal Transfer",H46,0) -> 0 | P46: =IF(E46="Saving Allocation",H46,0) -> 0 | Q46: =IF(E46="Investment",H46,0) -> 0 | R46: =IF(E46="Debt Repayment",H46,0) -> 0 | S46: =IF(E46="Joint Account",H46,0) -> 0 | T46: =IF(E46="Income",H46,0) -> 0
A47: 3/2/26 -> 9/2/26 | G47: Total Debt Repayments | H47: =SUMIF(E31:E39,"Debt Repayment",H31:H39) -> 375 | N47: =IF(OR(E47="Personal Expense",E47="Recurring Expense"),H47,0) -> 0 | O47: =IF(E47="Internal Transfer",H47,0) -> 0 | P47: =IF(E47="Saving Allocation",H47,0) -> 0 | Q47: =IF(E47="Investment",H47,0) -> 0 | R47: =IF(E47="Debt Repayment",H47,0) -> 0 | S47: =IF(E47="Joint Account",H47,0) -> 0 | T47: =IF(E47="Income",H47,0) -> 0
A48: 3/2/26 -> 9/2/26 | G48: TOTAL | H48: =H43+H46+H42+H44+H47+H45 -> 1007.63 | N48: =IF(OR(E48="Personal Expense",E48="Recurring Expense"),H48,0) -> 0 | O48: =IF(E48="Internal Transfer",H48,0) -> 0 | P48: =IF(E48="Saving Allocation",H48,0) -> 0 | Q48: =IF(E48="Investment",H48,0) -> 0 | R48: =IF(E48="Debt Repayment",H48,0) -> 0 | S48: =IF(E48="Joint Account",H48,0) -> 0 | T48: =IF(E48="Income",H48,0) -> 0
A49: 3/2/26 -> 9/2/26 | G49: TRUE WEEKLY SURPLUS | H49: =H41-(H43+H46)-H42-H44-H47-H45 -> 71.12 | N49: =IF(OR(E49="Personal Expense",E49="Recurring Expense"),H49,0) -> 0 | O49: =IF(E49="Internal Transfer",H49,0) -> 0 | P49: =IF(E49="Saving Allocation",H49,0) -> 0 | Q49: =IF(E49="Investment",H49,0) -> 0 | R49: =IF(E49="Debt Repayment",H49,0) -> 0 | S49: =IF(E49="Joint Account",H49,0) -> 0 | T49: =IF(E49="Income",H49,0) -> 0
G50: TRUE WEEKLY SURPLUS W/O SAVINGS | H50: =H49+SUMIFS($H:$H,$A:$A,A49,$E:$E,"Saving Allocation") -> 201.12
A51: 3/2/26 -> 9/2/26 | N51: =IF(OR(E51="Personal Expense",E51="Recurring Expense"),H51,0) -> 0 | O51: =IF(E51="Internal Transfer",H51,0) -> 0 | P51: =IF(E51="Saving Allocation",H51,0) -> 0 | Q51: =IF(E51="Investment",H51,0) -> 0 | R51: =IF(E51="Debt Repayment",H51,0) -> 0 | S51: =IF(E51="Joint Account",H51,0) -> 0 | T51: =IF(E51="Income",H51,0) -> 0
A52: 10/2/26 -> 16/2/26 | B52: 10/2/26 -> 16/2/26 | C52: 46063 | D52: Pay Sapien | E52: Income | F52: Sapien | G52: WestPac Everyday | H52: 1345.75 | I52: Salary | N52: =IF(OR(E52="Personal Expense",E52="Recurring Expense"),H52,0) -> 0 | O52: =IF(E52="Internal Transfer",H52,0) -> 0 | P52: =IF(E52="Saving Allocation",H52,0) -> 0 | Q52: =IF(E52="Investment",H52,0) -> 0 | R52: =IF(E52="Debt Repayment",H52,0) -> 0 | S52: =IF(E52="Joint Account",H52,0) -> 0 | T52: =IF(E52="Income",H52,0) -> 1345.75
A53: 10/2/26 -> 16/2/26 | C53: 46063 | D53: Bills Contribution | E53: Recurring Expense | F53: WestPac Everyday | G53: Lily | H53: 150 | I53: Rent | N53: =IF(OR(E53="Personal Expense",E53="Recurring Expense"),H53,0) -> 150 | O53: =IF(E53="Internal Transfer",H53,0) -> 0 | P53: =IF(E53="Saving Allocation",H53,0) -> 0 | Q53: =IF(E53="Investment",H53,0) -> 0 | R53: =IF(E53="Debt Repayment",H53,0) -> 0 | S53: =IF(E53="Joint Account",H53,0) -> 0 | T53: =IF(E53="Income",H53,0) -> 0
A54: 10/2/26 -> 16/2/26 | C54: 46063 | D54: Reimboursement Lily | E54: Debt Repayment | F54: WestPac Everyday | G54: Lily | H54: 375 | I54: Debt | N54: =IF(OR(E54="Personal Expense",E54="Recurring Expense"),H54,0) -> 0 | O54: =IF(E54="Internal Transfer",H54,0) -> 0 | P54: =IF(E54="Saving Allocation",H54,0) -> 0 | Q54: =IF(E54="Investment",H54,0) -> 0 | R54: =IF(E54="Debt Repayment",H54,0) -> 375 | S54: =IF(E54="Joint Account",H54,0) -> 0 | T54: =IF(E54="Income",H54,0) -> 0
A55: 10/2/26 -> 16/2/26 | C55: 46063 | D55: Transfer To Joint Account | E55: Joint Account | F55: WestPac Everyday | G55: Joint Account | H55: 200 | I55: Housing | N55: =IF(OR(E55="Personal Expense",E55="Recurring Expense"),H55,0) -> 0 | O55: =IF(E55="Internal Transfer",H55,0) -> 0 | P55: =IF(E55="Saving Allocation",H55,0) -> 0 | Q55: =IF(E55="Investment",H55,0) -> 0 | R55: =IF(E55="Debt Repayment",H55,0) -> 0 | S55: =IF(E55="Joint Account",H55,0) -> 200 | T55: =IF(E55="Income",H55,0) -> 0
A56: 10/2/26 -> 16/2/26 | C56: 46063 | D56: BTC Buy | E56: Investment | F56: WestPac Everyday | G56: OKX | H56: 15 | I56: Investment | N56: =IF(OR(E56="Personal Expense",E56="Recurring Expense"),H56,0) -> 0 | O56: =IF(E56="Internal Transfer",H56,0) -> 0 | P56: =IF(E56="Saving Allocation",H56,0) -> 0 | Q56: =IF(E56="Investment",H56,0) -> 15 | R56: =IF(E56="Debt Repayment",H56,0) -> 0 | S56: =IF(E56="Joint Account",H56,0) -> 0 | T56: =IF(E56="Income",H56,0) -> 0
A57: 10/2/26 -> 16/2/26 | C57: 46063 | D57: Student Loan/Google One | E57: Debt Repayment | F57: WestPac Everyday | G57: LaBanquePostale | H57: 135 | I57: Debt | N57: =IF(OR(E57="Personal Expense",E57="Recurring Expense"),H57,0) -> 0 | O57: =IF(E57="Internal Transfer",H57,0) -> 0 | P57: =IF(E57="Saving Allocation",H57,0) -> 0 | Q57: =IF(E57="Investment",H57,0) -> 0 | R57: =IF(E57="Debt Repayment",H57,0) -> 135 | S57: =IF(E57="Joint Account",H57,0) -> 0 | T57: =IF(E57="Income",H57,0) -> 0
A58: 10/2/26 -> 16/2/26 | C58: 46064 | D58: Pizza LaTaverna | E58: Personal Expense | F58: WestPac Everyday | G58: External | H58: 27.94 | I58: Food/Drink | N58: =IF(OR(E58="Personal Expense",E58="Recurring Expense"),H58,0) -> 27.94 | O58: =IF(E58="Internal Transfer",H58,0) -> 0 | P58: =IF(E58="Saving Allocation",H58,0) -> 0 | Q58: =IF(E58="Investment",H58,0) -> 0 | R58: =IF(E58="Debt Repayment",H58,0) -> 0 | S58: =IF(E58="Joint Account",H58,0) -> 0 | T58: =IF(E58="Income",H58,0) -> 0
A59: 10/2/26 -> 16/2/26 | C59: 46065 | D59: Milshake Zanzanz | E59: Personal Expense | F59: WestPac Everyday | G59: External | H59: 10.5 | I59: Food/Drink | N59: =IF(OR(E59="Personal Expense",E59="Recurring Expense"),H59,0) -> 10.5 | O59: =IF(E59="Internal Transfer",H59,0) -> 0 | P59: =IF(E59="Saving Allocation",H59,0) -> 0 | Q59: =IF(E59="Investment",H59,0) -> 0 | R59: =IF(E59="Debt Repayment",H59,0) -> 0 | S59: =IF(E59="Joint Account",H59,0) -> 0 | T59: =IF(E59="Income",H59,0) -> 0
A60: 10/2/26 -> 16/2/26 | C60: 46066 | D60: Transport Miky | E60: Personal Expense | F60: WestPac Everyday | G60: External | H60: 10 | I60: Transport | N60: =IF(OR(E60="Personal Expense",E60="Recurring Expense"),H60,0) -> 10 | O60: =IF(E60="Internal Transfer",H60,0) -> 0 | P60: =IF(E60="Saving Allocation",H60,0) -> 0 | Q60: =IF(E60="Investment",H60,0) -> 0 | R60: =IF(E60="Debt Repayment",H60,0) -> 0 | S60: =IF(E60="Joint Account",H60,0) -> 0 | T60: =IF(E60="Income",H60,0) -> 0
A61: 10/2/26 -> 16/2/26 | C61: 46068 | D61: Vape Sydney | E61: Personal Expense | F61: WestPac Everyday | G61: External | H61: 50 | I61: Leisure | N61: =IF(OR(E61="Personal Expense",E61="Recurring Expense"),H61,0) -> 50 | O61: =IF(E61="Internal Transfer",H61,0) -> 0 | P61: =IF(E61="Saving Allocation",H61,0) -> 0 | Q61: =IF(E61="Investment",H61,0) -> 0 | R61: =IF(E61="Debt Repayment",H61,0) -> 0 | S61: =IF(E61="Joint Account",H61,0) -> 0 | T61: =IF(E61="Income",H61,0) -> 0
A62: 10/2/26 -> 16/2/26 | C62: 46068 | D62: Joint Account Buffer | E62: Joint Account | F62: WestPac Everyday | G62: Joint Account | H62: 100 | I62: Housing | N62: =IF(OR(E62="Personal Expense",E62="Recurring Expense"),H62,0) -> 0 | O62: =IF(E62="Internal Transfer",H62,0) -> 0 | P62: =IF(E62="Saving Allocation",H62,0) -> 0 | Q62: =IF(E62="Investment",H62,0) -> 0 | R62: =IF(E62="Debt Repayment",H62,0) -> 0 | S62: =IF(E62="Joint Account",H62,0) -> 100 | T62: =IF(E62="Income",H62,0) -> 0
A63: 10/2/26 -> 16/2/26 | C63: 46069 | D63: Alchool IGA | E63: Personal Expense | F63: WestPac Everyday | G63: External | H63: 27.48 | I63: Food/Drink | N63: =IF(OR(E63="Personal Expense",E63="Recurring Expense"),H63,0) -> 27.48 | O63: =IF(E63="Internal Transfer",H63,0) -> 0 | P63: =IF(E63="Saving Allocation",H63,0) -> 0 | Q63: =IF(E63="Investment",H63,0) -> 0 | R63: =IF(E63="Debt Repayment",H63,0) -> 0 | S63: =IF(E63="Joint Account",H63,0) -> 0 | T63: =IF(E63="Income",H63,0) -> 0
A64: 10/2/26 -> 16/2/26 | N64: =IF(OR(E64="Personal Expense",E64="Recurring Expense"),H64,0) -> 0 | O64: =IF(E64="Internal Transfer",H64,0) -> 0 | P64: =IF(E64="Saving Allocation",H64,0) -> 0 | Q64: =IF(E64="Investment",H64,0) -> 0 | R64: =IF(E64="Debt Repayment",H64,0) -> 0 | S64: =IF(E64="Joint Account",H64,0) -> 0 | T64: =IF(E64="Income",H64,0) -> 0
A65: 10/2/26 -> 16/2/26 | B65: Pay | H65: =SUMIF(E52:E63,"Income",H52:H63) -> 1345.75 | N65: =IF(OR(E65="Personal Expense",E65="Recurring Expense"),H65,0) -> 0 | O65: =IF(E65="Internal Transfer",H65,0) -> 0 | P65: =IF(E65="Saving Allocation",H65,0) -> 0 | Q65: =IF(E65="Investment",H65,0) -> 0 | R65: =IF(E65="Debt Repayment",H65,0) -> 0 | S65: =IF(E65="Joint Account",H65,0) -> 0 | T65: =IF(E65="Income",H65,0) -> 0
A66: 10/2/26 -> 16/2/26 | F66: Total Household Expenses | H66: =SUMIF(E52:E63,"Joint Account",H52:H63) -> 300 | N66: =IF(OR(E66="Personal Expense",E66="Recurring Expense"),H66,0) -> 0 | O66: =IF(E66="Internal Transfer",H66,0) -> 0 | P66: =IF(E66="Saving Allocation",H66,0) -> 0 | Q66: =IF(E66="Investment",H66,0) -> 0 | R66: =IF(E66="Debt Repayment",H66,0) -> 0 | S66: =IF(E66="Joint Account",H66,0) -> 0 | T66: =IF(E66="Income",H66,0) -> 0
A67: 10/2/26 -> 16/2/26 | B67: Total Reccuring Expenses | H67: =SUMIF(E52:E63,"Recurring Expense",H52:H63) -> 150 | N67: =IF(OR(E67="Personal Expense",E67="Recurring Expense"),H67,0) -> 0 | O67: =IF(E67="Internal Transfer",H67,0) -> 0 | P67: =IF(E67="Saving Allocation",H67,0) -> 0 | Q67: =IF(E67="Investment",H67,0) -> 0 | R67: =IF(E67="Debt Repayment",H67,0) -> 0 | S67: =IF(E67="Joint Account",H67,0) -> 0 | T67: =IF(E67="Income",H67,0) -> 0
A68: 10/2/26 -> 16/2/26 | B68: Total Investing | H68: =SUMIF(E52:E63,"Investment",H52:H63) -> 15 | N68: =IF(OR(E68="Personal Expense",E68="Recurring Expense"),H68,0) -> 0 | O68: =IF(E68="Internal Transfer",H68,0) -> 0 | P68: =IF(E68="Saving Allocation",H68,0) -> 0 | Q68: =IF(E68="Investment",H68,0) -> 0 | R68: =IF(E68="Debt Repayment",H68,0) -> 0 | S68: =IF(E68="Joint Account",H68,0) -> 0 | T68: =IF(E68="Income",H68,0) -> 0
A69: 10/2/26 -> 16/2/26 | B69: Total Savings | H69: =SUMIF(E52:E63,"Saving Allocation",H52:H63) -> 0 | N69: =IF(OR(E69="Personal Expense",E69="Recurring Expense"),H69,0) -> 0 | O69: =IF(E69="Internal Transfer",H69,0) -> 0 | P69: =IF(E69="Saving Allocation",H69,0) -> 0 | Q69: =IF(E69="Investment",H69,0) -> 0 | R69: =IF(E69="Debt Repayment",H69,0) -> 0 | S69: =IF(E69="Joint Account",H69,0) -> 0 | T69: =IF(E69="Income",H69,0) -> 0
A70: 10/2/26 -> 16/2/26 | B70: Total Personnal Expenses | H70: =SUMIF(E52:E63,"Personal Expense",H52:H63) -> 125.92 | N70: =IF(OR(E70="Personal Expense",E70="Recurring Expense"),H70,0) -> 0 | O70: =IF(E70="Internal Transfer",H70,0) -> 0 | P70: =IF(E70="Saving Allocation",H70,0) -> 0 | Q70: =IF(E70="Investment",H70,0) -> 0 | R70: =IF(E70="Debt Repayment",H70,0) -> 0 | S70: =IF(E70="Joint Account",H70,0) -> 0 | T70: =IF(E70="Income",H70,0) -> 0
A71: 10/2/26 -> 16/2/26 | G71: Total Debt Repayments | H71: =SUMIF(E52:E63,"Debt Repayment",H52:H63) -> 510 | N71: =IF(OR(E71="Personal Expense",E71="Recurring Expense"),H71,0) -> 0 | O71: =IF(E71="Internal Transfer",H71,0) -> 0 | P71: =IF(E71="Saving Allocation",H71,0) -> 0 | Q71: =IF(E71="Investment",H71,0) -> 0 | R71: =IF(E71="Debt Repayment",H71,0) -> 0 | S71: =IF(E71="Joint Account",H71,0) -> 0 | T71: =IF(E71="Income",H71,0) -> 0
A72: 10/2/26 -> 16/2/26 | G72: TOTAL | H72: =H67+H70+H66+H68+H71 -> 1100.92 | N72: =IF(OR(E72="Personal Expense",E72="Recurring Expense"),H72,0) -> 0 | O72: =IF(E72="Internal Transfer",H72,0) -> 0 | P72: =IF(E72="Saving Allocation",H72,0) -> 0 | Q72: =IF(E72="Investment",H72,0) -> 0 | R72: =IF(E72="Debt Repayment",H72,0) -> 0 | S72: =IF(E72="Joint Account",H72,0) -> 0 | T72: =IF(E72="Income",H72,0) -> 0
A73: 10/2/26 -> 16/2/26 | G73: TRUE WEEKLY SURPLUS | H73: =H65-(H67+H70)-H66-H68-H71 -> 244.83 | N73: =IF(OR(E73="Personal Expense",E73="Recurring Expense"),H73,0) -> 0 | O73: =IF(E73="Internal Transfer",H73,0) -> 0 | P73: =IF(E73="Saving Allocation",H73,0) -> 0 | Q73: =IF(E73="Investment",H73,0) -> 0 | R73: =IF(E73="Debt Repayment",H73,0) -> 0 | S73: =IF(E73="Joint Account",H73,0) -> 0 | T73: =IF(E73="Income",H73,0) -> 0
G74: TRUE WEEKLY SURPLUS W/O SAVINGS | H74: =H73+SUMIFS($H:$H,$A:$A,A73,$E:$E,"Saving Allocation") -> 244.83
A75: 10/2/26 -> 16/2/26 | N75: =IF(OR(E75="Personal Expense",E75="Recurring Expense"),H75,0) -> 0 | O75: =IF(E75="Internal Transfer",H75,0) -> 0 | P75: =IF(E75="Saving Allocation",H75,0) -> 0 | Q75: =IF(E75="Investment",H75,0) -> 0 | R75: =IF(E75="Debt Repayment",H75,0) -> 0 | S75: =IF(E75="Joint Account",H75,0) -> 0 | T75: =IF(E75="Income",H75,0) -> 0
A76: 17/2/26 -> 23/2/26 | B76: 17/2/26 -> 23/2/26 | C76: 46070 | D76: Pay Sapien | E76: Income | F76: Sapien | G76: WestPac Everyday | H76: 1192.92 | I76: Salary | N76: =IF(OR(E76="Personal Expense",E76="Recurring Expense"),H76,0) -> 0 | O76: =IF(E76="Internal Transfer",H76,0) -> 0 | P76: =IF(E76="Saving Allocation",H76,0) -> 0 | Q76: =IF(E76="Investment",H76,0) -> 0 | R76: =IF(E76="Debt Repayment",H76,0) -> 0 | S76: =IF(E76="Joint Account",H76,0) -> 0 | T76: =IF(E76="Income",H76,0) -> 1192.92
A77: 17/2/26 -> 23/2/26 | C77: 46070 | D77: Bills Contribution | E77: Recurring Expense | F77: WestPac Everyday | G77: Lily | H77: 150 | I77: Rent | N77: =IF(OR(E77="Personal Expense",E77="Recurring Expense"),H77,0) -> 150 | O77: =IF(E77="Internal Transfer",H77,0) -> 0 | P77: =IF(E77="Saving Allocation",H77,0) -> 0 | Q77: =IF(E77="Investment",H77,0) -> 0 | R77: =IF(E77="Debt Repayment",H77,0) -> 0 | S77: =IF(E77="Joint Account",H77,0) -> 0 | T77: =IF(E77="Income",H77,0) -> 0
A78: 17/2/26 -> 23/2/26 | C78: 46070 | D78: Reimboursement Lily | E78: Debt Repayment | F78: WestPac Everyday | G78: Lily | H78: 375 | I78: Debt | N78: =IF(OR(E78="Personal Expense",E78="Recurring Expense"),H78,0) -> 0 | O78: =IF(E78="Internal Transfer",H78,0) -> 0 | P78: =IF(E78="Saving Allocation",H78,0) -> 0 | Q78: =IF(E78="Investment",H78,0) -> 0 | R78: =IF(E78="Debt Repayment",H78,0) -> 375 | S78: =IF(E78="Joint Account",H78,0) -> 0 | T78: =IF(E78="Income",H78,0) -> 0
A79: 17/2/26 -> 23/2/26 | C79: 46070 | D79: Transfer To Joint Account | E79: Joint Account | F79: WestPac Everyday | G79: Joint Account | H79: 200 | I79: Housing | N79: =IF(OR(E79="Personal Expense",E79="Recurring Expense"),H79,0) -> 0 | O79: =IF(E79="Internal Transfer",H79,0) -> 0 | P79: =IF(E79="Saving Allocation",H79,0) -> 0 | Q79: =IF(E79="Investment",H79,0) -> 0 | R79: =IF(E79="Debt Repayment",H79,0) -> 0 | S79: =IF(E79="Joint Account",H79,0) -> 200 | T79: =IF(E79="Income",H79,0) -> 0
A80: 17/2/26 -> 23/2/26 | C80: 46070 | D80: Bills Contribution (Next Week) | E80: Recurring Expense | F80: WestPac Everyday | G80: Lily | H80: 150 | I80: Housing | N80: =IF(OR(E80="Personal Expense",E80="Recurring Expense"),H80,0) -> 150 | O80: =IF(E80="Internal Transfer",H80,0) -> 0 | P80: =IF(E80="Saving Allocation",H80,0) -> 0 | Q80: =IF(E80="Investment",H80,0) -> 0 | R80: =IF(E80="Debt Repayment",H80,0) -> 0 | S80: =IF(E80="Joint Account",H80,0) -> 0 | T80: =IF(E80="Income",H80,0) -> 0
A81: 17/2/26 -> 23/2/26 | C81: 46070 | D81: Reimboursement Lily (Next Week) | E81: Debt Repayment | F81: WestPac Everyday | G81: Lily | H81: 375 | I81: Debt | N81: =IF(OR(E81="Personal Expense",E81="Recurring Expense"),H81,0) -> 0 | O81: =IF(E81="Internal Transfer",H81,0) -> 0 | P81: =IF(E81="Saving Allocation",H81,0) -> 0 | Q81: =IF(E81="Investment",H81,0) -> 0 | R81: =IF(E81="Debt Repayment",H81,0) -> 375 | S81: =IF(E81="Joint Account",H81,0) -> 0 | T81: =IF(E81="Income",H81,0) -> 0
A82: 17/2/26 -> 23/2/26 | C82: 46070 | D82: Transfer To Joint Account (Next Week) | E82: Joint Account | F82: WestPac Everyday | G82: Joint Account | H82: 200 | I82: Housing | N82: =IF(OR(E82="Personal Expense",E82="Recurring Expense"),H82,0) -> 0 | O82: =IF(E82="Internal Transfer",H82,0) -> 0 | P82: =IF(E82="Saving Allocation",H82,0) -> 0 | Q82: =IF(E82="Investment",H82,0) -> 0 | R82: =IF(E82="Debt Repayment",H82,0) -> 0 | S82: =IF(E82="Joint Account",H82,0) -> 200 | T82: =IF(E82="Income",H82,0) -> 0
A83: 17/2/26 -> 23/2/26 | C83: 46076 | D83: Water Bottle Airport | E83: Personal Expense | F83: WestPac Everyday | G83: External | H83: 4.5 | I83: Food/Drink | N83: =IF(OR(E83="Personal Expense",E83="Recurring Expense"),H83,0) -> 4.5 | O83: =IF(E83="Internal Transfer",H83,0) -> 0 | P83: =IF(E83="Saving Allocation",H83,0) -> 0 | Q83: =IF(E83="Investment",H83,0) -> 0 | R83: =IF(E83="Debt Repayment",H83,0) -> 0 | S83: =IF(E83="Joint Account",H83,0) -> 0 | T83: =IF(E83="Income",H83,0) -> 0
A84: 17/2/26 -> 23/2/26 | N84: =IF(OR(E84="Personal Expense",E84="Recurring Expense"),H84,0) -> 0 | O84: =IF(E84="Internal Transfer",H84,0) -> 0 | P84: =IF(E84="Saving Allocation",H84,0) -> 0 | Q84: =IF(E84="Investment",H84,0) -> 0 | R84: =IF(E84="Debt Repayment",H84,0) -> 0 | S84: =IF(E84="Joint Account",H84,0) -> 0 | T84: =IF(E84="Income",H84,0) -> 0
A85: 17/2/26 -> 23/2/26 | B85: Pay | H85: =SUMIF(E76:E83,"Income",H76:H83) -> 1192.92 | N85: =IF(OR(E85="Personal Expense",E85="Recurring Expense"),H85,0) -> 0 | O85: =IF(E85="Internal Transfer",H85,0) -> 0 | P85: =IF(E85="Saving Allocation",H85,0) -> 0 | Q85: =IF(E85="Investment",H85,0) -> 0 | R85: =IF(E85="Debt Repayment",H85,0) -> 0 | S85: =IF(E85="Joint Account",H85,0) -> 0 | T85: =IF(E85="Income",H85,0) -> 0
A86: 17/2/26 -> 23/2/26 | F86: Total Household Expenses | H86: =SUMIF(E76:E83,"Joint Account",H76:H83) -> 400 | N86: =IF(OR(E86="Personal Expense",E86="Recurring Expense"),H86,0) -> 0 | O86: =IF(E86="Internal Transfer",H86,0) -> 0 | P86: =IF(E86="Saving Allocation",H86,0) -> 0 | Q86: =IF(E86="Investment",H86,0) -> 0 | R86: =IF(E86="Debt Repayment",H86,0) -> 0 | S86: =IF(E86="Joint Account",H86,0) -> 0 | T86: =IF(E86="Income",H86,0) -> 0
A87: 17/2/26 -> 23/2/26 | B87: Total Reccuring Expenses | H87: =SUMIF(E76:E83,"Recurring Expense",H76:H83) -> 300 | N87: =IF(OR(E87="Personal Expense",E87="Recurring Expense"),H87,0) -> 0 | O87: =IF(E87="Internal Transfer",H87,0) -> 0 | P87: =IF(E87="Saving Allocation",H87,0) -> 0 | Q87: =IF(E87="Investment",H87,0) -> 0 | R87: =IF(E87="Debt Repayment",H87,0) -> 0 | S87: =IF(E87="Joint Account",H87,0) -> 0 | T87: =IF(E87="Income",H87,0) -> 0
A88: 17/2/26 -> 23/2/26 | B88: Total Investing | H88: =SUMIF(E76:E83,"Investment",H76:H83) -> 0 | N88: =IF(OR(E88="Personal Expense",E88="Recurring Expense"),H88,0) -> 0 | O88: =IF(E88="Internal Transfer",H88,0) -> 0 | P88: =IF(E88="Saving Allocation",H88,0) -> 0 | Q88: =IF(E88="Investment",H88,0) -> 0 | R88: =IF(E88="Debt Repayment",H88,0) -> 0 | S88: =IF(E88="Joint Account",H88,0) -> 0 | T88: =IF(E88="Income",H88,0) -> 0
A89: 17/2/26 -> 23/2/26 | B89: Total Savings | H89: =SUMIF(E76:E83,"Saving Allocation",H76:H83) -> 0 | N89: =IF(OR(E89="Personal Expense",E89="Recurring Expense"),H89,0) -> 0 | O89: =IF(E89="Internal Transfer",H89,0) -> 0 | P89: =IF(E89="Saving Allocation",H89,0) -> 0 | Q89: =IF(E89="Investment",H89,0) -> 0 | R89: =IF(E89="Debt Repayment",H89,0) -> 0 | S89: =IF(E89="Joint Account",H89,0) -> 0 | T89: =IF(E89="Income",H89,0) -> 0
A90: 17/2/26 -> 23/2/26 | B90: Total Personnal Expenses | H90: =SUMIF(E76:E83,"Personal Expense",H76:H83) -> 4.5 | N90: =IF(OR(E90="Personal Expense",E90="Recurring Expense"),H90,0) -> 0 | O90: =IF(E90="Internal Transfer",H90,0) -> 0 | P90: =IF(E90="Saving Allocation",H90,0) -> 0 | Q90: =IF(E90="Investment",H90,0) -> 0 | R90: =IF(E90="Debt Repayment",H90,0) -> 0 | S90: =IF(E90="Joint Account",H90,0) -> 0 | T90: =IF(E90="Income",H90,0) -> 0
A91: 17/2/26 -> 23/2/26 | G91: Total Debt Repayments | H91: =SUMIF(E76:E83,"Debt Repayment",H76:H83) -> 750 | N91: =IF(OR(E91="Personal Expense",E91="Recurring Expense"),H91,0) -> 0 | O91: =IF(E91="Internal Transfer",H91,0) -> 0 | P91: =IF(E91="Saving Allocation",H91,0) -> 0 | Q91: =IF(E91="Investment",H91,0) -> 0 | R91: =IF(E91="Debt Repayment",H91,0) -> 0 | S91: =IF(E91="Joint Account",H91,0) -> 0 | T91: =IF(E91="Income",H91,0) -> 0
A92: 17/2/26 -> 23/2/26 | G92: TOTAL | H92: =H87+H90+H86+H88+H91 -> 1454.5 | N92: =IF(OR(E92="Personal Expense",E92="Recurring Expense"),H92,0) -> 0 | O92: =IF(E92="Internal Transfer",H92,0) -> 0 | P92: =IF(E92="Saving Allocation",H92,0) -> 0 | Q92: =IF(E92="Investment",H92,0) -> 0 | R92: =IF(E92="Debt Repayment",H92,0) -> 0 | S92: =IF(E92="Joint Account",H92,0) -> 0 | T92: =IF(E92="Income",H92,0) -> 0
A93: 17/2/26 -> 23/2/26 | G93: TRUE WEEKLY SURPLUS | H93: =H85-(H87+H90)-H86-H88-H91 -> -261.58 | N93: =IF(OR(E93="Personal Expense",E93="Recurring Expense"),H93,0) -> 0 | O93: =IF(E93="Internal Transfer",H93,0) -> 0 | P93: =IF(E93="Saving Allocation",H93,0) -> 0 | Q93: =IF(E93="Investment",H93,0) -> 0 | R93: =IF(E93="Debt Repayment",H93,0) -> 0 | S93: =IF(E93="Joint Account",H93,0) -> 0 | T93: =IF(E93="Income",H93,0) -> 0
G94: TRUE WEEKLY SURPLUS W/O SAVINGS | H94: =H93+SUMIFS($H:$H,$A:$A,A93,$E:$E,"Saving Allocation") -> -261.58
A95: 17/2/26 -> 23/2/26 | N95: =IF(OR(E95="Personal Expense",E95="Recurring Expense"),H95,0) -> 0 | O95: =IF(E95="Internal Transfer",H95,0) -> 0 | P95: =IF(E95="Saving Allocation",H95,0) -> 0 | Q95: =IF(E95="Investment",H95,0) -> 0 | R95: =IF(E95="Debt Repayment",H95,0) -> 0 | S95: =IF(E95="Joint Account",H95,0) -> 0 | T95: =IF(E95="Income",H95,0) -> 0
A96: 24/2/26 -> 2/3/26 | B96: 24/2/26 -> 2/3/26 | C96: - | D96: No pay | E96: Review | F96: - | G96: - | H96: 0 | I96: - | N96: =IF(OR(E96="Personal Expense",E96="Recurring Expense"),H96,0) -> 0 | O96: =IF(E96="Internal Transfer",H96,0) -> 0 | P96: =IF(E96="Saving Allocation",H96,0) -> 0 | Q96: =IF(E96="Investment",H96,0) -> 0 | R96: =IF(E96="Debt Repayment",H96,0) -> 0 | S96: =IF(E96="Joint Account",H96,0) -> 0 | T96: =IF(E96="Income",H96,0) -> 0
A97: 24/2/26 -> 2/3/26 | C97: 46077 | D97: Tip Uber | E97: Personal Expense | F97: WestPac Everyday | G97: External | H97: 2.5 | I97: Transport | N97: =IF(OR(E97="Personal Expense",E97="Recurring Expense"),H97,0) -> 2.5 | O97: =IF(E97="Internal Transfer",H97,0) -> 0 | P97: =IF(E97="Saving Allocation",H97,0) -> 0 | Q97: =IF(E97="Investment",H97,0) -> 0 | R97: =IF(E97="Debt Repayment",H97,0) -> 0 | S97: =IF(E97="Joint Account",H97,0) -> 0 | T97: =IF(E97="Income",H97,0) -> 0
A98: 24/2/26 -> 2/3/26 | C98: 46077 | D98: Uber Home | E98: Personal Expense | F98: WestPac Everyday | G98: External | H98: 35.42 | I98: Transport | N98: =IF(OR(E98="Personal Expense",E98="Recurring Expense"),H98,0) -> 35.42 | O98: =IF(E98="Internal Transfer",H98,0) -> 0 | P98: =IF(E98="Saving Allocation",H98,0) -> 0 | Q98: =IF(E98="Investment",H98,0) -> 0 | R98: =IF(E98="Debt Repayment",H98,0) -> 0 | S98: =IF(E98="Joint Account",H98,0) -> 0 | T98: =IF(E98="Income",H98,0) -> 0
A99: 24/2/26 -> 2/3/26 | C99: 46077 | D99: Uber Work | E99: Personal Expense | F99: WestPac Everyday | G99: External | H99: 52.35 | I99: Transport | N99: =IF(OR(E99="Personal Expense",E99="Recurring Expense"),H99,0) -> 52.35 | O99: =IF(E99="Internal Transfer",H99,0) -> 0 | P99: =IF(E99="Saving Allocation",H99,0) -> 0 | Q99: =IF(E99="Investment",H99,0) -> 0 | R99: =IF(E99="Debt Repayment",H99,0) -> 0 | S99: =IF(E99="Joint Account",H99,0) -> 0 | T99: =IF(E99="Income",H99,0) -> 0
A100: 24/2/26 -> 2/3/26 | C100: 46077 | D100: Zanzanz (FoodWork) | E100: Personal Expense | F100: WestPac Everyday | G100: External | H100: 13.9 | I100: Food/Drink | N100: =IF(OR(E100="Personal Expense",E100="Recurring Expense"),H100,0) -> 13.9 | O100: =IF(E100="Internal Transfer",H100,0) -> 0 | P100: =IF(E100="Saving Allocation",H100,0) -> 0 | Q100: =IF(E100="Investment",H100,0) -> 0 | R100: =IF(E100="Debt Repayment",H100,0) -> 0 | S100: =IF(E100="Joint Account",H100,0) -> 0 | T100: =IF(E100="Income",H100,0) -> 0
A101: 24/2/26 -> 2/3/26 | C101: 46077 | D101: Transport Miky | E101: Personal Expense | F101: WestPac Everyday | G101: External | H101: 10 | I101: Transport | N101: =IF(OR(E101="Personal Expense",E101="Recurring Expense"),H101,0) -> 10 | O101: =IF(E101="Internal Transfer",H101,0) -> 0 | P101: =IF(E101="Saving Allocation",H101,0) -> 0 | Q101: =IF(E101="Investment",H101,0) -> 0 | R101: =IF(E101="Debt Repayment",H101,0) -> 0 | S101: =IF(E101="Joint Account",H101,0) -> 0 | T101: =IF(E101="Income",H101,0) -> 0
...

Sheet Work Income Tracker
B4: Driscoll's INCOME TRACKER (Farm Mandatory Job)
B5: TIME RELATED | G5: BASE RATE | H5: PAY RELATED | K5: NOTES | L5: TAXE RELATED | N5: SUPERANNUATION
B6: Weeks Count | C6: Driscolls | D6: Days Worked | E6: Hours / Day | F6: Hours Worked | G6: Base Rate in AU$ | H6: Gross Weekly income in AU$ | I6: Net Weekly income in AU$ | J6: Monthly Income in AU$ | K6: Notes | L6: PAYG (Tax Withheld) | M6: PAYG (%) | N6: UniSuper
B7: 1st | C7: 45455 | D7: 3 | E7: =IFERROR(F7/D7,"") -> 7 | F7: 21 | G7: 28.26 | H7: =(G7*F7) -> 593.46 | I7: 504.46 | K7: $245 fees (Rent+Transport) / $259.46 Net | L7: =H7-I7 -> 89 | M7: =(H7-I7)/H7 -> 0.14996798 | N7: 65.28
B8: 2nd | C8: 45462 | D8: 4 | E8: =IFERROR(F8/D8,"") -> 7.125 | F8: 28.5 | G8: 28.26 | H8: =(G8*F8) -> 805.41 | I8: 684.41 | K8: $245 fees (Rent+Transport) / $439.41 Net | L8: =H8-I8 -> 121 | M8: =(H8-I8)/H8 -> 0.15023404 | N8: 88.6
B9: 3rd | C9: 45469 | D9: 5 | E9: =IFERROR(F9/D9,"") -> 7.5 | F9: 37.5 | G9: 28.26 | H9: =(G9*F9) -> 1059.75 | I9: 900.75 | K9: $245 fees (Rent+Transport) / $655.75 Net | L9: =H9-I9 -> 159 | M9: =(H9-I9)/H9 -> 0.15003539 | N9: 116.57
B10: 4th | C10: 45476 | D10: 5 | E10: =IFERROR(F10/D10,"") -> 7.5 | F10: 37.5 | G10: 28.26 | H10: =(G10*F10) -> 1059.75 | I10: 900.75 | J10: =SUM(I7:I10) -> 2990.37 | K10: $245 fees (Rent+Transport) / $655.75 Net | L10: =H10-I10 -> 159 | M10: =(H10-I10)/H10 -> 0.15003539 | N10: 121.87
B11: NEW FINANCIAL YEAR
B12: 5th | C12: 45483 | D12: 5 | E12: =IFERROR(F12/D12,"") -> 7.5 | F12: 37.5 | G12: 29.33 | H12: =(G12*F12) -> 1099.875 | I12: 934.88 | K12: $245 fees (Rent+Transport) / $689.88 Net | L12: =H12-I12 -> 164.995 | M12: =(H12-I12)/H12 -> 0.1500125 | N12: 126.49
B13: 6th | C13: 45490 | D13: 5 | E13: =IFERROR(F13/D13,"") -> 7.5 | F13: 37.5 | G13: 29.33 | H13: =(G13*F13) -> 1099.875 | I13: 934.88 | L13: =H13-I13 -> 164.995 | M13: =(H13-I13)/H13 -> 0.1500125 | N13: 126.49
B14: 7th | C14: 45497 | D14: 5 | E14: =IFERROR(F14/D14,"") -> 7.5 | F14: 37.5 | G14: 29.33 | H14: =((G14*F14)+(G15*F15)+(G16*F16)) -> 1328.635 | I14: 1129.64 | K14: 5 Extra Hours during the week | L14: =(SUM(H14:H16)-I14) -> 198.995 | M14: =((H14+H15+H16)-I14)/(H14+H15+H16) -> 0.14977402 | N14: 126.49
D15: 0 | E15: =IFERROR(F15/D15,"") | F15: 3 | G15: 41.06
D16: 0 | E16: =IFERROR(F16/D16,"") | F16: 2 | G16: 52.79
B17: 8th | C17: 45504 | D17: 5 | E17: =IFERROR(F17/D17,"") -> 7.5 | F17: 37.5 | G17: 29.33 | H17: =(G17*F17) -> 1099.875 | I17: 934.88 | J17: =SUM(I12:I17) -> 3934.28 | L17: =H17-I17 -> 164.995 | M17: =(H17-I17)/H17 -> 0.1500125 | N17: 126.49
B18: 9th | C18: 45511 | D18: 5 | E18: =IFERROR(F18/D18,"") -> 7.5 | F18: 37.5 | G18: 29.33 | H18: =(G18*F18) -> 1099.875 | I18: 934.88 | L18: =H18-I18 -> 164.995 | M18: =(H18-I18)/H18 -> 0.1500125 | N18: 126.49
B19: 10th | C19: 45518 | D19: 5 | E19: =IFERROR(F19/D19,"") -> 7.5 | F19: 37.5 | G19: 29.33 | H19: =(G19*F19) -> 1099.875 | I19: 934.88 | L19: =H19-I19 -> 164.995 | M19: =(H19-I19)/H19 -> 0.1500125 | N19: 126.49
B20: 11th | C20: 45525 | D20: 5 | E20: =IFERROR(F20/D20,"") -> 7.5 | F20: 37.5 | G20: 29.33 | H20: =G20*F20 -> 1099.875 | I20: 934.88 | L20: =H20-I20 -> 164.995 | M20: =(H20-I20)/H20 -> 0.1500125 | N20: 126.49
B21: 12th | C21: 45532 | D21: 4 | E21: =IFERROR(F21/D21,"") -> 6.875 | F21: 27.5 | G21: 29.33 | H21: =G21*F21 -> 806.575 | I21: 685 | J21: =SUM(I18:I21) -> 3489.64 | K21: Fired on the Thursday at lunchtime | L21: =H21-I21 -> 121.575 | M21: =(H21-I21)/H21 -> 0.15072994 | N21: 93.11
B22: / | C22: AVERAGE | D22: =AVERAGE(D7:D10,D12:D14,D17:D21) -> 4.6666667 | E22: =AVERAGE(E7:E10,E12:E14,E17:E21) -> 7.375 | F22: =AVERAGE(F7:F10,F12:F14,F17:F21) -> 34.541667 | G22: =AVERAGE(G7:G10,G12:G14,G17:G21) -> 28.973333 | H22: =AVERAGE(H7:H21) -> 1021.0692 | I22: =AVERAGE(I7:I21) -> 867.8575 | J22: =AVERAGE(J7:J18,J20:J21) -> 3471.43 | K22: / | L22: =AVERAGE(L7:L21) -> 153.21167 | M22: =AVERAGE(M1:M21) -> 0.15007098 | N22: /
B23: / | C23: TOTAL | D23: =SUM(D7:D10,D12:D14,D17:D21) -> 56 | E23: / | F23: =SUM(F7:F21) -> 419.5 | G23: / | H23: =SUM(H7:H21) -> 12252.83 | I23: =SUM(I7:I21) -> 10414.29 | J23: / | K23: / | L23: =SUM(L7:L19,L20:L21) -> 1838.54 | M23: / | N23: =SUM(N7:N21) -> 1370.86
B26: Tamarua (Perth) INCOME TRACKER (Farm Mandatory Job)
B27: TIME RELATED | G27: BASE RATE | H27: PAY RELATED | K27: NOTES | L27: TAXE RELATED | N27: SUPERANNUATION
B28: Weeks Count | C28: Tamarua | D28: Days Worked | E28: Hours / Day | F28: Hours Worked | G28: Base Rate in AU$ | H28: Gross Fortnight income in AU$ | I28: Net Fornight income in AU$ | J28: Monthly Income in AU$ | K28: Notes | L28: PAYG (Tax Withheld) | M28: PAYG (%) | N28: UniSuper
B29: 1st + 2nd | C29: 45547 | D29: 14 | E29: =IFERROR(F29/D29,"") -> 4.9635714 | F29: 69.49 | G29: 30 | H29: =(G29*F29) -> 2084.7 | I29: 1771.7 | L29: =H29-I29 -> 313 | M29: =(H29-I29)/H29 -> 0.15014151 | N29: 239.74
B30: 3rd + 4th | C30: 45561 | D30: 14 | E30: =IFERROR(F30/D30,"") -> 5.6092857 | F30: 78.53 | G30: 30 | H30: =(G30*F30) -> 2355.9 | I30: 2002.9 | L30: =H30-I30 -> 353 | M30: =(H30-I30)/H30 -> 0.14983658 | N30: 270.93
B31: 5th + 6th | C31: 45575 | D31: 14 | E31: =IFERROR(F31/D31,"") -> 7.8585714 | F31: 110.02 | G31: 30 | H31: 3300.6 | I31: 2805.6 | J31: =SUM(I29:I31) -> 6580.2 | L31: =H31-I31 -> 495 | N31: 379.57
B32: / | C32: AVERAGE | D32: =AVERAGE(D29:D31) -> 14 | E32: =AVERAGE(E29:E31) -> 6.1438095 | F32: =AVERAGE(F29:F31) -> 86.013333 | G32: =AVERAGE(G29:G30) -> 30 | H32: =AVERAGE(H29:H31) -> 2580.4 | I32: =AVERAGE(I29:I31) -> 2193.4 | J32: / | K32: / | L32: =AVERAGE(L29:L31) -> 387 | M32: =AVERAGE(M25:M30) -> 0.14998904 | N32: /
B33: / | C33: TOTAL | D33: =SUM(D29:D31) -> 42 | E33: / | F33: =SUM(F29:F31) -> 258.04 | G33: / | H33: =SUM(H29:H31) -> 7741.2 | I33: =SUM(I29:I31) -> 6580.2 | J33: =SUM(J29:J31) -> 6580.2 | K33: / | L33: =SUM(L29:L31) -> 1161 | M33: / | N33: =SUM(N29:N31) -> 890.24
B36: Consolidated Carpentry INCOME TRACKER
B37: TIME RELATED | H37: BASE RATE | I37: PAY RELATED | L37: NOTES | M37: TAXE RELATED | P37: SUPERANNUATION
B38: Weeks Count | C38: Consolidated Carpentry | D38: Days Worked | E38: Hours / Day | F38: Hours Worked | G38: With extra hours | H38: Base Rate in AU$ | I38: Gross Weekly income in AU$ | J38: Net Weekly income in AU$ | K38: Monthly Income in AU$ | L38: Notes | M38: PAYG (Tax Withheld) | N38: PAYG (%) | O38: Tax to Pay on ABN | P38: UniSuper
B39: 1st | C39: 45683 | D39: 5 | E39: =IFERROR(F39/D39,"") -> 6.6 | F39: 33 | G39: 33 | H39: 25.9 | I39: =(H39*F39) -> 854.7 | J39: 598.7 | M39: =I39-J39 -> 256 | N39: =(I39-J39)/I39 -> 0.2995203 | O39: / | P39: 98.29
B40: 2nd | C40: 45690 | D40: 5 | E40: =IFERROR(F40/D40,"") -> 6 | F40: 30 | G40: =SUM(F40:F42) -> 36 | H40: 25.9 | I40: =((H40*F40)+(H41*F41)+(H42*F42)) -> 1061.9 | J40: 743.9 | L40: 6 Extra Hours During the week | M40: =I40-J40 -> 318 | N40: =(I40-J40)/I40 -> 0.29946323 | O40: / | P40: 89.36
D41: 1 | E41: =IFERROR(F41/D41,"") -> 2 | F41: 2 | H41: 38.85
D42: 1 | E42: =IFERROR(F42/D42,"") -> 4 | F42: 4 | H42: 51.8
B43: 3rd | C43: 45697 | D43: 5 | E43: =IFERROR(F43/D43,"") -> 7.6 | F43: 38 | G43: 38 | H43: 25.9 | I43: =(H43*F43) -> 984.2 | J43: 836.2 | M43: =I43-J43 -> 148 | N43: =(I43-J43)/I43 -> 0.15037594 | O43: / | P43: 113.18
B44: 4th | C44: 45704 | D44: 5 | E44: =IFERROR(F44/D44,"") -> 7.6 | F44: 38 | G44: =SUM(F44:F45) -> 39 | H44: 25.9 | I44: =((H44*F44)+(H45*F45)) -> 1023.05 | J44: 870.05 | K44: =SUM(J39:J45) -> 3048.85 | L44: 1 Extra Hour during the week | M44: =I44-J44 -> 153 | N44: =(I44-J44)/I44 -> 0.14955281 | O44: / | P44: 113.18
D45: 0 | E45: =IFERROR(F45/D45,"") | F45: 1 | H45: 38.85
B46: 5th | C46: 45711 | D46: 5 | E46: =IFERROR(F46/D46,"") -> 7.6 | F46: 38 | G46: =SUM(F46:F48) -> 55.5 | H46: 25.9 | I46: =((H46*F46)+(H47*F47)+(H48*F48)) -> 1800.05 | J46: 1530.05 | L46: 17.5 Extra Hours during the week | M46: =I46-J46 -> 270 | N46: =(I46-J46)/I46 -> 0.14999583 | O46: / | P46: 113.18
D47: 1 | E47: =IFERROR(F47/D47,"") -> 7 | F47: 7 | H47: 38.85
D48: 1 | E48: =IFERROR(F48/D48,"") -> 10.5 | F48: 10.5 | H48: 51.8
B49: 6th | C49: 45718 | D49: 3 | E49: =IFERROR(F49/D49,"") -> 8 | F49: 24 | G49: =SUM(F49:F52) -> 33 | H49: 25.9 | I49: =((H49*F49)+(H50*F50)+(H51*F51)+(H52*F52)) -> 997.15 | J49: 847.15 | L49: 9 Extra Hours During the week | M49: =I49-J49 -> 150 | N49: =(I49-J49)/I49 -> 0.15042872 | O49: / | P49: 77.44
D50: 0 | E50: =IFERROR(F50/D50,"") | F50: 2 | H50: 25.9
D51: 1 | E51: =IFERROR(F51/D51,"") -> 3 | F51: 3 | H51: 38.85
D52: 1 | E52: =IFERROR(F52/D52,"") -> 4 | F52: 4 | H52: 51.8
B53: 7th | C53: 45725 | D53: 5 | E53: =IFERROR(F53/D53,"") -> 7.6 | F53: 38 | G53: =SUM(F53:F54) -> 40.5 | H53: 25.9 | I53: =((H53*F53)+(H54*F54)) -> 1081.325 | J53: 919.32 | L53: 2.5 Extra Hours during the week | M53: =I53-J53 -> 162.005 | N53: =(I53-J53)/I53 -> 0.14982082 | O53: / | P53: 113.18
D54: 0 | E54: =IFERROR(F54/D54,"") | F54: 2.5 | H54: 38.85
B55: 8th | C55: 45732 | D55: 4 | E55: =IFERROR(F55/D55,"") -> 8 | F55: 32 | G55: =SUM(F55:F57) -> 46 | H55: 25.9 | I55: =((H55*F55)+(H56*F56)+(H57*F57)) -> 1502.2 | J55: 1277.2 | K55: =SUM(J46:J57) -> 4573.72 | L55: 14 Extra Hours During the week | M55: =I55-J55 -> 225 | N55: =(I55-J55)/I55 -> 0.14978032 | O55: / | P55: 95.31
D56: 1 | E56: =IFERROR(F56/D56,"") -> 4 | F56: 4 | H56: 38.85
D57: 1 | E57: =IFERROR(F57/D57,"") -> 10 | F57: 10 | H57: 51.8
B58: 9th | C58: 45739 | D58: 5 | E58: =IFERROR(F58/D58,"") -> 7.6 | F58: 38 | G58: =SUM(F58:F60) -> 65 | H58: 25.9 | I58: =((H58*F58)+(H59*F59)+(H60*F60)) -> 2227.4 | J58: 1893.4 | L58: 27 Extra Hours During the week | M58: =I58-J58 -> 334 | N58: =(I58-J58)/I58 -> 0.14995062 | O58: / | P58: 113.18
D59: 1 | E59: =IFERROR(F59/D59,"") -> 12 | F59: 12 | H59: 38.85
D60: 1 | E60: =IFERROR(F60/D60,"") -> 15 | F60: 15 | H60: 51.8
B61: 10th | C61: 45746 | D61: 5 | E61: =IFERROR(F61/D61,"") -> 7.6 | F61: 38 | G61: =SUM(F61:F62) -> 43 | H61: 25.9 | I61: =((H61*F61)+(H62*F62)) -> 1178.45 | J61: 1001.45 | L61: 5 Extra Hours during the week | M61: =I61-J61 -> 177 | N61: =(I61-J61)/I61 -> 0.15019729 | O61: / | P61: 113.18
D62: 1 | E62: =IFERROR(F62/D62,"") -> 5 | F62: 5 | H62: 38.85
B63: TRANSITION TO ABN REGIME
B64: 11th | C64: 45751 | D64: 5 | E64: =IFERROR(F64/D64,"") -> 7.8 | F64: 39 | G64: =F64 -> 39 | H64: 25.9 | I64: =F64*H64 -> 1010.1 | L64: / | M64: / | N64: =AVERAGE(N43:N62) -> 0.15001279 | O64: =I64*N64 -> 151.52792 | P64: /
B65: 12th | C65: 45758 | D65: 5 | E65: =IFERROR(F65/D65,"") -> 7.932 | F65: 39.66 | G65: =F65 -> 39.66 | H65: 25.9 | I65: =H65*F65 -> 1027.194 | L65: / | M65: / | N65: =AVERAGE(N43:N62) -> 0.15001279 | O65: =I65*N65 -> 154.09224 | P65: /
B66: 13th | C66: 45764 | D66: 4 | E66: =IFERROR(F66/D66,"") -> 7.6875 | F66: 30.75 | G66: =F66 -> 30.75 | H66: 25.9 | I66: =H66*F66 -> 796.425 | L66: / | M66: / | N66: =AVERAGE(N43:N62) -> 0.15001279 | O66: =I66*N66 -> 119.47394 | P66: /
B67: 14th | C67: 45771 | D67: 3 | E67: =IFERROR(F67/D67,"") -> 7.75 | F67: 23.25 | G67: =F67 -> 23.25 | H67: 25.9 | I67: =H67*F67 -> 602.175 | L67: / | M67: / | N67: =AVERAGE(N43:N62) -> 0.15001279 | O67: =I67*N67 -> 90.333954 | P67: /
B68: 15th | C68: 45779 | D68: 4 | E68: =IFERROR(F68/D68,"") -> 7.25 | F68: 29 | G68: =F68 -> 29 | H68: 25.9 | I68: =H68*F68 -> 751.1 | L68: / | M68: / | N68: =AVERAGE(N43:N62) -> 0.15001279 | O68: =I68*N68 -> 112.67461 | P68: /
B69: 16th | C69: 45786 | D69: 5 | E69: =IFERROR(F69/D69,"") -> 7.45 | F69: 37.25 | G69: =F69 -> 37.25 | H69: 25.9 | I69: =H69*F69 -> 964.775 | L69: / | M69: / | N69: =AVERAGE(N43:N62) -> 0.15001279 | O69: =I69*N69 -> 144.72859 | P69: /
B70: 17th | C70: 45793 | D70: 4 | E70: =IFERROR(F70/D70,"") -> 7.1875 | F70: 28.75 | G70: =F70 -> 28.75 | H70: 25.9 | I70: =H70*F70 -> 744.625 | L70: / | M70: / | N70: =AVERAGE(N43:N62) -> 0.15001279 | O70: =I70*N70 -> 111.70328 | P70: /
B71: 18th | C71: 45801 | D71: 6 | E71: =IFERROR(F71/D71,"") -> 7.6666667 | F71: 46 | G71: =F71 -> 46 | H71: 25.9 | I71: =H71*F71 -> 1191.4 | L71: 5.25 Extra Hours during the week (No extra Rate) | M71: / | N71: =AVERAGE(N43:N62) -> 0.15001279 | O71: =I71*N71 -> 178.72524 | P71: /
B72: / | C72: AVERAGE | D72: =AVERAGE(D39:D40,D43:D44,D46,D53,D55,D58,D61,D64:D71) -> 4.7058824 | E72: =AVERAGE(E39:E44,E46:E49,E51:E53,E55:E62,E64:E71) -> 7.2904713 | F72: =AVERAGE(F39,(F40+F41+F42),F43,(F44+F45),(F46+F47+F48),(F49+F50+F51+F52),(F53+F54),(F55+F56+F57),(F58+F59+F60),(F61+F62),F64:F71) -> 39.036667 | H72: =AVERAGE(H39:H40,H43:H44,H46,H49:H50,H53) -> 25.9 | I72: =AVERAGE(I39:I71) -> 1099.9011 | J72: =AVERAGE(J39:J71) -> 1051.742 | K72: =AVERAGE(K39:K71) -> 3811.285 | L72: 87.25 Extra Hours in Total | M72: =AVERAGE(M39:M71) -> 219.3005 | N72: =AVERAGE(N39:N71) -> 0.16662157 | O72: / | P72: /
B73: / | C73: TOTAL | D73: =SUM(D39:D71) -> 94 | E73: / | F73: =SUM(F39:F71) -> 702.66 | H73: / | I73: =SUM(I39:I71) -> 19798.219 | J73: =SUM(J39:J71) -> 10517.42 | K73: / | L73: / | M73: =SUM(M39:M71) -> 2193.005 | N73: / | O73: =SUM(O64:O71) -> 1063.2598 | P73: =SUM(P39:P71) -> 1039.48
B74: NEW FINANCIAL YEAR
B76: Avad Recruitment INCOME TRACKER
B77: TIME RELATED | G77: BASE RATE | H77: PAY RELATED | K77: NOTES | L77: TAXE RELATED | N77: SUPERANNUATION
B78: Weeks Count | C78: Avad Recruitment | D78: Days Worked | E78: Hours / Day | F78: Hours Worked | G78: Base Rate in AU$ | H78: Gross Weekly in AU$ | I78: Net Weekly Income | J78: Monthly Income | K78: Notes | L78: PAYG (Tax Withheld) | M78: PAYG (%) | N78: UniSuper
B79: 1st | C79: 45834 | D79: 4 | E79: =IFERROR(F79/D79,"") -> 7.75 | F79: 31 | G79: 34 | H79: 1141.76 | I79: 970.76 | K79: Travel Allowance : $87.76 | L79: =H79-I79 -> 171 | M79: =(H79-I79)/H79 -> 0.14976878 | N79: 121.21
B80: 2nd | C80: 45841 | D80: 3 | E80: =IFERROR(F80/D80,"") -> 6.6666667 | F80: 20 | G80: 34 | H80: 745.82 | I80: 633.82 | K80: Travel Allowance : $65.82 | L80: =H80-I80 -> 112 | M80: =(H80-I80)/H80 -> 0.15017028 | N80: 81.6
B81: NEW FINANCIAL YEAR
B82: 3rd | C82: 45848 | D82: 3 | E82: =IFERROR(F82/D82,"") -> 7.5 | F82: 22.5 | G82: 34 | H82: 1251.02 | I82: 1066.02 | K82: Travel Allowance : $65.82 | L82: =H82-I82 -> 185 | M82: =(H82-I82)/H82 -> 0.14787933 | N82: 91.8
D83: 1 | E83: =IFERROR(F83/D83,"") -> 2 | F83: 2 | G83: 47.6
D84: 1 | E84: =IFERROR(F84/D84,"") -> 5 | F84: 5 | G84: 61.2
B85: 4th | C85: 45855 | D85: 1 | E85: =IFERROR(F85/D85,"") -> 8 | F85: 8 | G85: 34 | H85: 293.94 | I85: 249.94 | K85: Travel Allowance : $21.94 | L85: =H85-I85 -> 44 | M85: =(H85-I85)/H85 -> 0.14969041 | N85: 32.64
B86: 5th | C86: 45862 | D86: 1 | E86: =IFERROR(F86/D86,"") -> 7 | F86: 7 | G86: 34 | H86: 259.94 | I86: 220.94 | K86: Travel Allowance : $21.94 | L86: =H86-I86 -> 39 | M86: =(H86-I86)/H86 -> 0.15003462 | N86: 28.56
B87: / | C87: AVERAGE | F87: / | G87: =AVERAGE(G79,G82:G86) -> 40.8 | H87: =AVERAGE(H80:H86) -> 637.68 | I87: =AVERAGE(I79,I82:I86) -> 626.915 | J87: / | K87: Avad Recruitment period reconstructed from recovered payslips. YTD values may be less reliable due to FY crossover and payroll formatting. Use individual payslips as source of truth. | L87: =AVERAGE(L82:L86) -> 89.333333 | M87: =AVERAGE(M79,M82:M86) -> 0.14934329 | N87: /
B88: / | C88: TOTAL | F88: = | G88: / | H88: =SUM(H79,H80:H86) -> 3692.48 | I88: =SUM(I79,I80:I86) -> 3141.48 | J88: / | K88: Travel Allowance : $263.28 | L88: =SUM(L82:L86) -> 268 | M88: / | N88: =SUM(N79,N82:N86) -> 274.21
B92: PadBuilt INCOME TRACKER
B93: TIME RELATED | G93: BASE RATE | H93: PAY RELATED | I93: NOTES | J93: TAXE RELATED
B94: Weeks Count | C94: PadBulit | D94: Days Worked | E94: Hours / Day | F94: Hours Worked | G94: Base Rate in AU$ | H94: Gross Weekly income in AU$ | I94: Notes | J94: PAYG (%) | K94: Tax To Pay on ABN
B95: 1st | C95: 45864 | D95: 5 | E95: 6.4 | F95: 32 | G95: 35 | H95: 1120 | I95: / | J95: 0.15 | K95: 168
B96: 2nd | C96: 45877 | D96: 2 | E96: 6.92 | F96: 13.83 | G96: 35 | H96: 484.05 | I96: / | J96: 0.15 | K96: 72.61
B97: 3rd | C97: 45887 | D97: 6 | E97: 6.83 | F97: 41 | G97: 35 | H97: 1435 | I97: / | J97: 0.15 | K97: 215.25
B98: / | C98: AVERAGE | D98: 4.33 | E98: 6.72 | F98: 28.94 | G98: 35 | H98: 1013.02 | I98: / | J98: / | K98: /
B99: / | C99: TOTAL | D99: =SUM(D95:D97) -> 13 | E99: / | F99: =SUM(F95:F97) -> 86.83 | G99: / | H99: =SUM(H95:H97) -> 3039.05 | I99: / | J99: / | K99: =SUM(K95:K97) -> 455.86
B102: Modelling INCOME TRACKER
B103: TIME RELATED | G103: BASE RATE | H103: PAY RELATED | I103: NOTES | J103: TAXE RELATED
B104: Weeks Count | C104: EveryDayMood | D104: Days Worked | E104: Hours / Day | F104: Hours Worked | G104: Base Rate in AU$ | H104: Gross Weekly income in AU$ | I104: Notes | J104: PAYG (%) | K104: Tax To Pay on ABN
B105: 1st | C105: 45944 | D105: 1 | E105: =IFERROR(F105/D105,"") -> 4 | F105: 4 | G105: 75 | H105: =((G105*F105)+30) -> 330 | I105: / | J105: 0.15 | K105: =H105*J105 -> 49.5
B106: / | C106: AVERAGE | D106: / | E106: / | F106: / | G106: / | H106: / | I106: / | J106: / | K106: /
B107: / | C107: TOTAL | D107: / | E107: / | F107: / | G107: / | H107: =H105 -> 330 | I107: / | J107: / | K107: =K105 -> 49.5
B110: SAPIEN INCOME TRACKER
B111: TIME RELATED | G111: BASE RATE | H111: PAY RELATED | K111: NOTES | L111: TAXE RELATED | N111: PROJECTIONS | O111: SUPERANNUATION
B112: Weeks Count | C112: SAPIEN | D112: Days Worked | E112: Hours / Day | F112: Hours Worked | G112: Base Rate in AU$ | H112: Gross Weekly income in AU$ | I112: Net Weekly income in AU$ | J112: Monthly Income in AU$ | K112: Notes | L112: PAYG (Tax Withheld) | M112: PAYG (%) | N112: Projection Net Weekly income in AU$ | O112: UniSuper
B113: 1st | C113: 45923 | D113: 3 | E113: =IFERROR(F113/D113,"") -> 7 | F113: 21 | G113: 31.2 | H113: =(G113*F113) -> 655.2 | I113: 557.2 | K113: 1st week - Worked 3days | L113: =H113-I113 -> 98 | M113: =(H113-I113)/H113 -> 0.14957265 | N113: =H113-(H113*M152) -> 556.91618 | O113: 78.62
B114: 2nd | C114: 45930 | D114: 5 | E114: =IFERROR(F114/D114,"") -> 6.034 | F114: 30.17 | G114: 31.2 | H114: =(G114*F114) -> 941.304 | I114: 800.2 | L114: =H114-I114 -> 141.104 | M114: =(H114-I114)/H114 -> 0.14990269 | N114: =H114-(H114*M152) -> 800.10291 | O114: 112.94
B115: 3rd | C115: 45937 | D115: 5 | E115: =IFERROR(F115/D115,"") -> 6.85 | F115: 34.25 | G115: 31.2 | H115: =(G115*F115) -> 1068.6 | I115: 908.6 | J115: =I113+I114+I115 -> 2266 | L115: =H115-I115 -> 160 | M115: =(H115-I115)/H115 -> 0.14972862 | N115: =H115-(H115*M152) -> 908.30377 | O115: 128.23
...

Sheet Investing
A2: CRYPTOCURRENCY | H2: ASX ETF | T2: ASX STOCK PICKING | Z2: WALL STREET STOCK PICKING
B4: BITCOIN INVESTMENT | H4: BGBL INVESTMENT (ASX) | N4: VGE INVESTMENT (ASX) | T4: CSL INVESTMENT (ASX) | Z4: VOO INVESTMENT (S&P 500)
B5: Date | C5: Amount Invested | D5: Amount Bitcoin | E5: Bitcoin Price | H5: Date | I5: Amount Invested | J5: Shares Amount | K5: Share Price | N5: Date | O5: Amount Invested | P5: Shares Amount | Q5: Share Price | T5: Date | U5: Amount Invested | V5: Amount shares | W5: Share Price | Z5: Date | AA5: Amount Invested | AB5: Amount Shares | AC5: Share Price
B6: 45952 | C6: 40 | D6: 0.00023653 | E6: 168492 | H6: 46125 | I6: 80 | J6: 1.037 | K6: 77.14 | N6: 46125 | O6: 20 | P6: 0.2278 | Q6: 87.76 | T6: 46133 | U6: 30 | V6: 0.22 | W6: 136.34 | Z6: 46135 | AA6: 67.52 | AB6: 0.0989 | AC6: 652.35
B7: 45958 | C7: 0 | D7: 0.0004357 | E7: 171542 | H7: 46128 | I7: 80 | J7: 1.0198 | K7: 78.44 | N7: 46128 | O7: 20 | P7: 0.2227 | Q7: 89.8
B8: 45960 | C8: 14 | D8: 8.172e-05 | E8: 171301 | H8: 46134 | I8: 80 | J8: 1.0134 | K8: 78.94 | N8: 46134 | O8: 20 | P8: 0.2205 | Q8: 90.69
B9: 45966 | C9: 35 | D9: 0.00022173 | E9: 157000 | H9: 46140 | I9: 28 | J9: 0.354 | K9: 79.09 | N9: 46140 | O9: 10 | P9: 0.1108 | Q9: 90.24 | T9: Total Bought (Buy) | U9: =SUM(U6:U8) -> 30 | V9: =SUM(V6:V8) -> 0.22 | W9: =U9/V9 -> 136.36364 | X9: <- AVERAGE PRICE BOUGHT | Z9: Total Bought (Buy) | AA9: =SUM(AA6:AA8) -> 67.52 | AB9: =SUM(AB6:AB8) -> 0.0989 | AC9: =AVERAGE(AC6:AC8) -> 652.35 | AD9: <- AVERAGE PRICE BOUGHT
B10: 45976 | C10: 10 | D10: 6.763e-05 | E10: 147851.7 | H10: 46148 | I10: 25 | J10: 0.3129 | K10: 79.89 | N10: 46148 | O10: 10 | P10: 0.1093 | Q10: 91.44 | T10: Current Price / Value | U10: =V9*W10 -> 21.5512 | W10: {=_xlfn.FIELDVALUE(U11,"Price")} -> 97.96 | Z10: Current Price / Value in USD | AA10: =AB9*AC10 -> 67.196616 | AC10: {=_xlfn.FIELDVALUE(AA12,"Price")} -> 679.44
B11: 45981 | C11: 30 | D11: 0.00021373 | E11: 140363.8 | H11: 46155 | I11: 25 | J11: 0.3083 | K11: 81.06 | N11: 46155 | O11: 10 | P11: 0.1091 | Q11: 91.64 | T11: Current Price | U11: #VALUE! | Z11: Current Price / Value in AUD | AA11: =AA10*AB15 -> 93.940869
B12: 45982 | C12: 30 | D12: 0.00022143 | E12: 134426.2 | T12: P/L | U12: =U10-U9 -> -8.4488 | Z12: Current Price | AA12: #VALUE!
B13: 46049 | C13: 14.99 | D13: 0.00011727 | E13: 127000 | T13: ROI | U13: =U12/U9 -> -0.28162667 | Z13: P/L | AA13: =AA10-AA9 -> -0.323384
B14: 46058 | C14: 14.99 | D14: 0.00013842 | E14: 107600 | Z14: ROI | AA14: =AA13/AA9 -> -0.004789455
B15: 46076 | C15: 14.99 | D15: 0.00015669 | E15: 95000 | Z15: USD/AUD | AA15: #VALUE! | AB15: {=_xlfn.FIELDVALUE(AA15,"Price")} -> 1.398
B16: 46099 | C16: 14.99 | D16: 0.00014319 | E16: 104000 | H16: Total Bought | I16: =SUM(I6:I15) -> 318 | J16: =SUM(J6:J15) -> 4.0454 | K16: =AVERAGE(K6:K15) -> 79.093333 | L16: <- AVERAGE PRICE BOUGHT | N16: Total Bought | O16: =SUM(O6:O15) -> 90 | P16: =SUM(P6:P15) -> 1.0002 | Q16: =AVERAGE(Q6:Q15) -> 90.261667 | R16: <- AVERAGE PRICE BOUGHT
B17: 46100 | C17: 14.99 | D17: 0.00014597 | E17: 102000 | H17: Curent Price / Value | I17: =J16*K17 -> 329.98328 | K17: {=_xlfn.FIELDVALUE(I18,"Price")} -> 81.57 | N17: Curent Price / Value | O17: =P16*Q17 -> 90.088014 | Q17: {=_xlfn.FIELDVALUE(O18,"Price")} -> 90.07
B18: 46100 | C18: 14.99 | D18: 0.00014895 | E18: 100000 | H18: BGBL VALUE REAL TIME | I18: #VALUE! | N18: BGBL VALUE REAL TIME | O18: #VALUE!
B19: 46103 | C19: 14.99 | D19: 0.00015113 | E19: 98000 | H19: P/L | I19: =I17-I16 -> 11.983278 | N19: P/L | O19: =O17-O16 -> 0.088014
B20: 46114 | C20: 14.99 | D20: 0.00015192 | E20: 98000 | H20: ROI | I20: =I19/I16 -> 0.037683264 | N20: ROI | O20: =O19/O16 -> 0.00097793333
B21: 46125 | C21: 14.99 | D21: 0.00014348 | E21: 101000
B22: 46128 | C22: 14.99 | D22: 0.00014438 | E22: 102500
B23: 46136 | C23: 14.99 | D23: 0.00013574 | E23: 109727
B24: 46140 | C24: 14.99 | D24: 0.00013743 | E24: 108341.7
B25: 46148 | C25: 14.99 | D25: 0.00013147 | E25: 113219.6
B26: 46155 | C26: 14.99 | D26: 0.00013604 | E26: 109431.6
B29: Total BTC Owned (ALL) | D29: =SUM(D6:D28) -> 0.00346055
B30: Total BTC Bought (Buy) | C30: =SUM(C6:C28) -> 368.86 | D30: =SUM(D8:D28,D6) -> 0.00302485 | E30: =AVERAGE(E6,E8:E28) -> 119762.73 | F30: <- AVERAGE PRICE BOUGHT
B31: Current Price / Value | C31: =D30*E31 -> 330.21314 | E31: {=_xlfn.FIELDVALUE(C32,"Price")} -> 109166.78
B32: BTC VALUE REAL TIME | C32: #VALUE!
B33: P/L | C33: =C31-C30 -> -38.646856
B34: ROI | C34: =C33/C30 -> -0.10477378

Sheet Stock Picking Scorecard
B2: STOCK PICKING SCORECARD | J2: BARÈME / RÈGLES
B3: SCORECARD | J3: GUIDE RAPIDE
B4: Critère | C4: Poids | D4: Score (0-5) | E4: Score pondéré | F4: Passage | G4: Notes | H4: Question clé | J4: Score | K4: Sens | L4: Lecture | M4: Action
B5: Qualité du business | C5: 20 | D5: 4.5 | E5: =C5*D5/5 -> 18 | F5: =IF(D5="","",IF(D5>=4,"Strong",IF(D5>=3,"OK","Weak"))) -> Strong | H5: Le business est-il compréhensible, utile et défendable? | J5: 0 | K5: Très mauvais | L5: Faiblesse majeure / incompréhension | M5: Stop
B6: Position concurrentielle | C6: 15 | D6: 4.5 | E6: =C6*D6/5 -> 13.5 | F6: =IF(D6="","",IF(D6>=4,"Strong",IF(D6>=3,"OK","Weak"))) -> Strong | H6: Pourquoi elle plutôt qu’un concurrent ? | J6: 1 | K6: Faible | L6: Problème sérieux | M6: Écarter
B7: Management & allocation du capital | C7: 15 | D7: 3 | E7: =C7*D7/5 -> 9 | F7: =IF(D7="","",IF(D7>=4,"Strong",IF(D7>=3,"OK","Weak"))) -> OK | H7: Le CEO/board gèrent-ils bien le capital ? | J7: 2 | K7: Moyen faible | L7: Peu convaincant | M7: Watchlist seulement
B8: Qualité financière | C8: 20 | D8: 4 | E8: =C8*D8/5 -> 16 | F8: =IF(D8="","",IF(D8>=4,"Strong",IF(D8>=3,"OK","Weak"))) -> Strong | H8: Le profit, le cash et le bilan sont-ils solides ? | J8: 3 | K8: Acceptable | L8: Base correcte | M8: Creuser davantage
B9: Résilience & risques | C9: 15 | D9: 3.5 | E9: =C9*D9/5 -> 10.5 | F9: =IF(D9="","",IF(D9>=4,"Strong",IF(D9>=3,"OK","Weak"))) -> OK | H9: Peut-elle absorber un choc sans casser la thèse ? | J9: 4 | K9: Bon | L9: Thèse solide | M9: Candidat sérieux
B10: Valorisation | C10: 15 | D10: 3.5 | E10: =C10*D10/5 -> 10.5 | F10: =IF(D10="","",IF(D10>=4,"Strong",IF(D10>=3,"OK","Weak"))) -> OK | H10: Le prix payé laisse-t-il une marge d’erreur ? | J10: 5 | K10: Très bon | L10: Qualité + prix | M10: Achat possible
B12: Total Score | D12: =SUM(E5:E10) -> 77.5 | J12: SEUILS
B13: Verdict | D13: =IF(D12="","",IF(D12>=80,"Très bon dossier",IF(D12>=70,"Bon dossier",IF(D12>=60,"Moyen / prix très important","Non pour l’instant")))) -> Bon dossier | J13: 80+ = Très bon dossier
B14: Red Flag fatale ? | D14: Non | E14: Si Oui, pas d’achat | J14: 70-79 = Bon dossier
B15: Décision | D15: =IF(OR(D14="Oui",D12=""),"",IF(D12>=80,"Achat possible / surveillance active",IF(D12>=70,"Surveiller ou petite ligne",IF(D12>=60,"Watchlist seulement","Rejeter pour l’instant")))) -> Surveiller ou petite ligne | J15: 60-69 = Moyen / prix très important
J16: <60 = Non pour l’instant
B17: RÈGLE : je n’achète pas une baisse. J’achète une thèse, un business et un prix.
J18: HARD STOPS
J19: • Business non compris
J20: • Bilan dangereux / dette excessive
J21: • Management douteux ou destructeur de capital
J22: • Pas de marge de sécurité
J23: • Thèse non écrite avant achat
